Workbook

Sheet 1_20251104.wos
A1: Publication Type | B1: Authors | C1: Book Authors | D1: Book Editors | E1: Book Group Authors | F1: Author Full Names | G1: Book Author Full Names | H1: Group Authors | I1: Article Title | J1: Source Title | K1: Book Series Title | L1: Book Series Subtitle | M1: Language | N1: Document Type | O1: Conference Title | P1: Conference Date | Q1: Conference Location | R1: Conference Sponsor | S1: Conference Host | T1: Author Keywords | U1: Keywords Plus | V1: Abstract | W1: Addresses | X1: Affiliations | Y1: Reprint Addresses | Z1: Email Addresses | AA1: Researcher Ids | AB1: ORCIDs | AC1: Funding Orgs | AD1: Funding Name Preferred | AE1: Funding Text | AF1: Cited References | AG1: Cited Reference Count | AH1: Times Cited, WoS Core | AI1: Times Cited, All Databases | AJ1: 180 Day Usage Count | AK1: Since 2013 Usage Count | AL1: Publisher | AM1: Publisher City | AN1: Publisher Address | AO1: ISSN | AP1: eISSN | AQ1: ISBN | AR1: Journal Abbreviation | AS1: Journal ISO Abbreviation | AT1: Publication Date | AU1: Publication Year | AV1: Volume | AW1: Issue | AX1: Part Number | AY1: Supplement | AZ1: Special Issue | BA1: Meeting Abstract | BB1: Start Page | BC1: End Page | BD1: Article Number | BE1: DOI | BF1: DOI Link | BG1: Book DOI | BH1: Early Access Date | BI1: Number of Pages | BJ1: WoS Categories | BK1: Web of Science Index | BL1: Research Areas | BM1: IDS Number | BN1: Pubmed Id | BO1: Open Access Designations | BP1: Highly Cited Status | BQ1: Hot Paper Status | BR1: Date of Export | BS1: UT (Unique WOS ID) | BT1: Web of Science Record
A2: J | B2: Jones, D; Snider, C; Nassehi, A; Yon, J; Hicks, B | F2: Jones, David; Snider, Chris; Nassehi, Aydin; Yon, Jason; Hicks, Ben | I2: Characterising the Digital Twin: A systematic literature review | J2: CIRP JOURNAL OF MANUFACTURING SCIENCE AND TECHNOLOGY | M2: English | N2: Review | T2: Digital Twin; Virtual Twin | U2: MODEL-PREDICTIVE CONTROL; SERVICE; DESIGN; FUTURE; METHODOLOGY; INFORMATION; ENVIRONMENT; AUTOMATION; SIMULATION | V2: While there has been a recent growth of interest in the Digital Twin, a variety of definitions employed across industry and academia remain. There is a need to consolidate research such to maintain a common understanding of the topic and ensure future research efforts are to be based on solid foundations. Through a systematic literature review and a thematic analysis of 92 Digital Twin publications from the last ten years, this paper provides a characterisation of the Digital Twin, identification of gaps in knowledge, and required areas of future research. In characterising the Digital Twin, the state of the concept, key terminology, and associated processes are identified, discussed, and consolidated to produce 13 characteristics (Physical Entity/Twin; Virtual Entity/Twin; Physical Environment; Virtual Environment; State; Realisation; Metrology; Twinning; Twinning Rate; Physical-to-Virtual Connection/Twinning; Virtual-to-Physical Connection/Twinning; Physical Processes; and Virtual Processes) and a complete framework of the Digital Twin and its process of operation. Following this characterisation, seven knowledge gaps and topics for future research focus are identified: Perceived Benefits; Digital Twin across the Product Life-Cycle; Use-Cases; Technical Implementations; Levels of Fidelity; Data Ownership; and Integration between Virtual Entities; each of which are required to realise the Digital Twin. (C) 2020 University of Bristol. | W2: [Jones, David; Snider, Chris; Nassehi, Aydin; Yon, Jason; Hicks, Ben] Univ Bristol, Dept Mech Engn, Queens Bldg, Bristol BS8 1TR, Avon, England | X2: University of Bristol | Y2: Jones, D (corresponding author), Univ Bristol, Dept Mech Engn, Queens Bldg, Bristol BS8 1TR, Avon, England. | Z2: david.jones@bristol.ac.uk; chris.snider@bristol.ac.uk; aydin.nassehi@bristol.ac.uk; jason.yon.02@bristol.ac.uk; ben.hicks@bristol.ac.uk | AA2: ; Hicks, Ben/A-9185-2010; Snider, Chris/AAR-6791-2020; Nassehi, Aydin/C-6810-2008 | AB2: Hicks, Ben/0000-0001-8294-4694; Snider, Chris/0000-0003-2692-110X; Yon, Jason/0000-0002-9384-4311; Nassehi, Aydin/0000-0003-3417-3391; Jones, David/0000-0002-6209-2698 | AC2: Engineering and Physical Sciences Research Council (EPSRC) [EP/R032696/1]; EPSRC [EP/R032696/1] Funding Source: UKRI | AD2: Engineering and Physical Sciences Research Council (EPSRC)(UK Research & Innovation (UKRI)Engineering & Physical Sciences Research Council (EPSRC)); EPSRC(UK Research & Innovation (UKRI)Engineering & Physical Sciences Research Council (EPSRC)) | AE2: The work reported in this paper has been undertaken as part of the project: Improving the product development process through integrated revision control and twinning of digital-physical models during prototyping. The work was conducted at the University of Bristol in the Design and Manufacturing Futures Lab (http://www.dmf-lab.co.uk) and is funded by the Engineering and Physical Sciences Research Council (EPSRC), Grant reference EP/R032696/1. | AG2: 112 | AH2: 1249 | AI2: 1442 | AJ2: 114 | AK2: 2197 | AL2: ELSEVIER | AM2: AMSTERDAM | AN2: RADARWEG 29, 1043 NX AMSTERDAM, NETHERLANDS | AO2: 1755-5817 | AP2: 1878-0016 | AR2: CIRP J MANUF SCI TEC | AS2: CIRP J. Manuf. Sci. Technol. | AT2: MAY | AU2: 2020 | AV2: 29 | AX2: A | BB2: 36 | BC2: 52 | BE2: 10.1016/j.cirpj.2020.02.002 | BF2: =HYPERLINK("http://dx.doi.org/10.1016/j.cirpj.2020.02.002","http://dx.doi.org/10.1016/j.cirpj.2020.02.002") -> http://dx.doi.org/10.1016/j.cirpj.2020.02.002 | BI2: 17 | BJ2: Engineering, Manufacturing | BK2: Science Citation Index Expanded (SCI-EXPANDED) | BL2: Engineering | BM2: LY2HI | BO2: Green Submitted, hybrid | BP2: Y | BQ2: N | BR2: 2025-11-04 | BS2: WOS:000540340800004 | BT2: =HYPERLINK("https%3A%2F%2Fwww.webofscience.com%2Fwos%2Fwoscc%2Ffull-record%2FWOS:000540340800004","View Full Record in Web of Science") -> View Full Record in Web of Science
A3: J | B3: Semeraro, C; Lezoche, M; Panetto, H; Dassisti, M | F3: Semeraro, Concetta; Lezoche, Mario; Panetto, Herve; Dassisti, Michele | I3: Digital twin paradigm: A systematic literature review | J3: COMPUTERS IN INDUSTRY | M3: English | N3: Review | T3: Digital twin; Industry 4; 0; Cyber-physical systems; Predictive manufacturing | U3: CYBER-PHYSICAL SYSTEMS; INDUSTRY 4.0; BIG DATA; DATA-DRIVEN; MANUFACTURING SYSTEM; FAULT-DIAGNOSIS; THINGS IOT; DESIGN; FUTURE; MODEL | V3: Manufacturing enterprises are facing the need to align themselves to the new information technologies (IT) and respond to the new challenges of variable market demand. One of the key enablers of this IT revolution toward Smart Manufacturing is the digital twin (DT). It embeds a virtual image of the real-ity constantly synchronized with the real operating scenario to provide sound information (knowledge model) to reality interpretation model to draw sound decisions. The paper aims at providing an up-to date picture of the main DT components, their features and interaction problems. The paper aims at clearly tracing the ongoing research and technical challenges in conceiving and building DTs as well, according to different application domains and related technologies. To this purpose, the main questions answered here are: 'What is a Digital Twin?'; 'Where is appropriate to use a Digital Twin?'; 'When has a Digital Twin to be developed?'; 'Why should a Digital Twin be used?'; 'How to design and implement a Digital Twin?'; 'What are the main challenges of implementing a Digital Twin?'. This study tries to answer to the previous questions funding on a wide systematic literature review of scientific research, tools, and technicalities in different application domains. (c) 2021 Elsevier B.V. All rights reserved. | W3: [Semeraro, Concetta; Lezoche, Mario; Panetto, Herve] Univ Lorraine, CNRS, CRAN, Nancy, France; [Semeraro, Concetta; Dassisti, Michele] Polytech Univ Bari, Dept Mech Management & Math DMMM, Bari, Italy | X3: Centre National de la Recherche Scientifique (CNRS); Universite de Lorraine; Politecnico di Bari | Y3: Semeraro, C (corresponding author), Univ Lorraine, CNRS, CRAN, Nancy, France. | Z3: concetta.semeraro@univ-lorraine.fr; mario.lezoche@univ-lorraine.fr; herve.panetto@univ-lorraine.fr; michele.dassisti@poliba.it | AA3: Dassisti, Michele/I-2668-2012; semeraro, concetta/AHA-4914-2022; Panetto, Herve/B-4626-2010; Lezoche, Mario/M-9236-2018; Panetto, Hervé/B-4626-2010 | AB3: Panetto, Herve/0000-0002-5537-2261; SEMERARO, CONCETTA/0000-0001-5152-0004; | AC3: Italian Ministry of Education, University and Research under the Programme Department of Excellence Legge [232/2016, CUP-D94I18000260001] | AD3: Italian Ministry of Education, University and Research under the Programme Department of Excellence Legge | AE3: This work was supported by the Italian Ministry of Education, University and Research under the Programme Department of Excellence Legge 232/2016 (Grant No. CUP-D94I18000260001) | AG3: 155 | AH3: 499 | AI3: 571 | AJ3: 56 | AK3: 879 | AL3: ELSEVIER | AM3: AMSTERDAM | AN3: RADARWEG 29, 1043 NX AMSTERDAM, NETHERLANDS | AO3: 0166-3615 | AP3: 1872-6194 | AR3: COMPUT IND | AS3: Comput. Ind. | AT3: SEP | AU3: 2021 | AV3: 130 | BD3: 103469 | BE3: 10.1016/j.compind.2021.103469 | BF3: =HYPERLINK("http://dx.doi.org/10.1016/j.compind.2021.103469","http://dx.doi.org/10.1016/j.compind.2021.103469") -> http://dx.doi.org/10.1016/j.compind.2021.103469 | BH3: MAY 2021 | BI3: 23 | BJ3: Computer Science, Interdisciplinary Applications | BK3: Science Citation Index Expanded (SCI-EXPANDED) | BL3: Computer Science | BM3: SM3WX | BO3: Green Submitted | BP3: Y | BQ3: N | BR3: 2025-11-04 | BS3: WOS:000657540900006 | BT3: =HYPERLINK("https%3A%2F%2Fwww.webofscience.com%2Fwos%2Fwoscc%2Ffull-record%2FWOS:000657540900006","View Full Record in Web of Science") -> View Full Record in Web of Science
A4: J | B4: Rathore, MM; Shah, SA; Shukla, D; Bentafat, E; Bakiras, S | F4: Rathore, M. Mazhar; Shah, Syed Attique; Shukla, Dhirendra; Bentafat, Elmahdi; Bakiras, Spiridon | I4: The Role of AI, Machine Learning, and Big Data in Digital Twinning: A Systematic Literature Review, Challenges, and Opportunities | J4: IEEE ACCESS | M4: English | N4: Review | T4: Big Data; Digital twin; Patents; Industries; Systematics; Tools; Libraries; Digital twin; artificial intelligence; machine learning; big data; industry 40 | U4: HEALTH MANAGEMENT; FAULT-DIAGNOSIS; DATA ANALYTICS; FRAMEWORK; TWINS; ARCHITECTURE; PROGNOSTICS; NETWORKS; SERVICES; DESIGN | V4: Digital twinning is one of the top ten technology trends in the last couple of years, due to its high applicability in the industrial sector. The integration of big data analytics and artificial intelligence/machine learning (AI-ML) techniques with digital twinning, further enriches its significance and research potential with new opportunities and unique challenges. To date, a number of scientific models have been designed and implemented related to this evolving topic. However, there is no systematic review of digital twinning, particularly focusing on the role of AI-ML and big data, to guide the academia and industry towards future developments. Therefore, this article emphasizes the role of big data and AI-ML in the creation of digital twins (DTs) or DT-based systems for various industrial applications, by highlighting the current state-of-the-art deployments. We performed a systematic review on top of multidisciplinary electronic bibliographic databases, in addition to existing patents in the field. Also, we identified development-tools that can facilitate various levels of the digital twinning. Further, we designed a big data driven and AI-enriched reference architecture that leads developers to a complete DT-enabled system. Finally, we highlighted the research potential of AI-ML for digital twinning by unveiling challenges and current opportunities. | W4: [Rathore, M. Mazhar; Bentafat, Elmahdi; Bakiras, Spiridon] Hamad Bin Khalifa Univ, Div Informat & Comp Technol, Coll Sci & Engn, Doha, Qatar; [Shah, Syed Attique] Univ Tartu, Inst Comp Sci, Data Syst Grp, EE-51009 Tartu, Estonia; [Shukla, Dhirendra] Univ New Brunswick, Dr J Herbert Smith Ctr, Fredericton, NB E3B 5A3, Canada | X4: Qatar Foundation (QF); Hamad Bin Khalifa University-Qatar; University of Tartu; University of New Brunswick | Y4: Bakiras, S (corresponding author), Hamad Bin Khalifa Univ, Div Informat & Comp Technol, Coll Sci & Engn, Doha, Qatar. | Z4: sbakiras@hbku.edu.qa | AA4: ; Shah, Syed Attique/ABD-6564-2021 | AB4: Shukla, Dhirendra/0000-0002-0036-714X; Shah, Syed Attique/0000-0003-2949-7391; Bakiras, Spiridon/0000-0002-8964-0746; Rathore, Muhammad Mazhar/0000-0002-0701-9850 | AG4: 175 | AH4: 270 | AI4: 327 | AJ4: 66 | AK4: 588 | AL4: IEEE-INST ELECTRICAL ELECTRONICS ENGINEERS INC | AM4: PISCATAWAY | AN4: 445 HOES LANE, PISCATAWAY, NJ 08855-4141 USA | AO4: 2169-3536 | AR4: IEEE ACCESS | AS4: IEEE Access | AU4: 2021 | AV4: 9 | BB4: 32030 | BC4: 32052 | BE4: 10.1109/ACCESS.2021.3060863 | BF4: =HYPERLINK("http://dx.doi.org/10.1109/ACCESS.2021.3060863","http://dx.doi.org/10.1109/ACCESS.2021.3060863") -> http://dx.doi.org/10.1109/ACCESS.2021.3060863 | BI4: 23 | BJ4: Computer Science, Information Systems; Engineering, Electrical & Electronic; Telecommunications | BK4: Science Citation Index Expanded (SCI-EXPANDED); Social Science Citation Index (SSCI) | BL4: Computer Science; Engineering; Telecommunications | BM4: QO8UB | BO4: Green Submitted, gold | BP4: Y | BQ4: N | BR4: 2025-11-04 | BS4: WOS:000623411600001 | BT4: =HYPERLINK("https%3A%2F%2Fwww.webofscience.com%2Fwos%2Fwoscc%2Ffull-record%2FWOS:000623411600001","View Full Record in Web of Science") -> View Full Record in Web of Science
A5: J | B5: van Dinter, R; Tekinerdogan, B; Catal, C | F5: van Dinter, Raymon; Tekinerdogan, Bedir; Catal, Cagatay | I5: Predictive maintenance using digital twins: A systematic literature review | J5: INFORMATION AND SOFTWARE TECHNOLOGY | M5: English | N5: Review | T5: Systematic literature review; Active learning; Digital twin; Predictive maintenance | U5: HEALTH MANAGEMENT; PROGNOSTICS | V5: Context: Predictive maintenance is a technique for creating a more sustainable, safe, and profitable industry. One of the key challenges for creating predictive maintenance systems is the lack of failure data, as the machine is frequently repaired before failure. Digital Twins provide a real-time representation of the physical machine and generate data, such as asset degradation, which the predictive maintenance algorithm can use. Since 2018, scientific literature on the utilization of Digital Twins for predictive maintenance has accelerated, indicating the need for a thorough review. Objective: This research aims to gather and synthesize the studies that focus on predictive maintenance using Digital Twins to pave the way for further research. Method: A systematic literature review (SLR) using an active learning tool is conducted on published primary studies on predictive maintenance using Digital Twins, in which 42 primary studies have been analyzed. Results: This SLR identifies several aspects of predictive maintenance using Digital Twins, including the objectives, application domains, Digital Twin platforms, Digital Twin representation types, approaches, abstraction levels, design patterns, communication protocols, twinning parameters, and challenges and solution directions. These results contribute to a Software Engineering approach for developing predictive maintenance using Digital Twins in academics and the industry. Conclusion: This study is the first SLR in predictive maintenance using Digital Twins. We answer key questions for designing a successful predictive maintenance model leveraging Digital Twins. We found that to this day, computational burden, data variety, and complexity of models, assets, or components are the key challenges in designing these models. | W5: [van Dinter, Raymon] Sioux Technol, Apeldoorn, Netherlands; [van Dinter, Raymon; Tekinerdogan, Bedir] Wageningen Univ & Res, Informat Technol Grp, Wageningen, Netherlands; [Catal, Cagatay] Qatar Univ, Dept Comp Sci & Engn, Doha, Qatar | X5: Wageningen University & Research; Qatar University | Y5: Tekinerdogan, B (corresponding author), Wageningen Univ & Res, Informat Technol Grp, Wageningen, Netherlands. | Z5: bedir.tekinerdogan@wur.nl | AA5: ; Tekinerdogan, Bedir/K-3639-2019; van+Dinter, Raymon/ABD-7476-2021; Catal, Cagatay/AAF-3929-2019 | AB5: Tekinerdogan, Bedir/0000-0002-8538-7261; Dinter, van, Raymon/0000-0002-1811-8803 | AG5: 114 | AH5: 196 | AI5: 232 | AJ5: 52 | AK5: 567 | AL5: ELSEVIER | AM5: AMSTERDAM | AN5: RADARWEG 29, 1043 NX AMSTERDAM, NETHERLANDS | AO5: 0950-5849 | AP5: 1873-6025 | AR5: INFORM SOFTWARE TECH | AS5: Inf. Softw. Technol. | AT5: NOV | AU5: 2022 | AV5: 151 | BD5: 107008 | BE5: 10.1016/j.infsof.2022.107008 | BF5: =HYPERLINK("http://dx.doi.org/10.1016/j.infsof.2022.107008","http://dx.doi.org/10.1016/j.infsof.2022.107008") -> http://dx.doi.org/10.1016/j.infsof.2022.107008 | BH5: JUL 2022 | BI5: 20 | BJ5: Computer Science, Information Systems; Computer Science, Software Engineering | BK5: Science Citation Index Expanded (SCI-EXPANDED) | BL5: Computer Science | BM5: 4V5BX | BO5: Green Accepted, hybrid | BP5: Y | BQ5: N | BR5: 2025-11-04 | BS5: WOS:000859493100007 | BT5: =HYPERLINK("https%3A%2F%2Fwww.webofscience.com%2Fwos%2Fwoscc%2Ffull-record%2FWOS:000859493100007","View Full Record in Web of Science") -> View Full Record in Web of Science
A6: J | B6: Liu, X; Jiang, D; Tao, B; Xiang, F; Jiang, GZ; Sun, Y; Kong, JY; Li, GF | F6: Liu, Xin; Jiang, Du; Tao, Bo; Xiang, Feng; Jiang, Guozhang; Sun, Ying; Kong, Jianyi; Li, Gongfa | I6: A systematic review of digital twin about physical entities, virtual models, twin data, and applications | J6: ADVANCED ENGINEERING INFORMATICS | M6: English | N6: Review | T6: Digital Twin; Physical entity; Virtual model; Twin data; Applications | U6: INDUSTRY 4.0; FRAMEWORK; OPERATIONS; QUALITY; ARCHITECTURE; PROGNOSTICS; PREDICTION; DESIGN; CLOUD | V6: The digital twin is a crucial technology for realizing smart manufacturing and industrial digital transformation, which has received extensive attention and research from industry and academia. After 20 years of development, the application area of digital twins has been pervasive. Due to the diversity of application areas, various reference models and research methods have been presented for the components of the digital twin. Therefore, this paper provides systematic research of current studies on the basic components of the digital twin. This paper analyzed 117 articles from 2017 to 2022. By clarifying the relationship between the digital twin and the cyberphysical system, it first clarified the definition, characteristics, and application areas of the digital twin. On this basis, the research methodology of the core components of the digital twin (physical entities, virtual models, and twin data) is analyzed. At the same time, the application areas of digital twins are analyzed and delineated, and the application potential of the digital twin is explored. Finally, the research results and future research recommendations are presented. | W6: [Liu, Xin; Tao, Bo; Kong, Jianyi; Li, Gongfa] Wuhan Univ Sci & Technol, Key Lab Met Equipment & Control Technol, Minist Educ, Wuhan 430081, Peoples R China; [Liu, Xin; Jiang, Du; Jiang, Guozhang; Kong, Jianyi; Li, Gongfa] Wuhan Univ Sci & Technol, Hubei Key Lab Mech Transmiss & Mfg Engn, Wuhan 430081, Peoples R China; [Jiang, Du; Tao, Bo; Xiang, Feng; Sun, Ying; Li, Gongfa] Wuhan Univ Sci & Technol, Res Ctr Biomimet Robot & Intelligent Measurement &, Wuhan 430081, Peoples R China; [Xiang, Feng; Sun, Ying] Wuhan Univ Sci & Technol, Precis Mfg Res Inst, Wuhan 430081, Peoples R China | X6: Wuhan University of Science & Technology; Wuhan University of Science & Technology; Wuhan University of Science & Technology; Wuhan University of Science & Technology | Y6: Li, GF (corresponding author), Wuhan Univ Sci & Technol, Key Lab Met Equipment & Control Technol, Minist Educ, Wuhan 430081, Peoples R China.;Jiang, D; Li, GF (corresponding author), Wuhan Univ Sci & Technol, Hubei Key Lab Mech Transmiss & Mfg Engn, Wuhan 430081, Peoples R China.;Jiang, D; Li, GF (corresponding author), Wuhan Univ Sci & Technol, Res Ctr Biomimet Robot & Intelligent Measurement &, Wuhan 430081, Peoples R China. | Z6: jiangdu@wust.edu.cn; ligongfa@wust.edu.cn | AA6: Liu, Xin/KYQ-8886-2024; sun, yong/HPD-0054-2023; jiang, guo/OIS-8385-2025; Bo, Tao/AFE-7417-2022 | AB6: Liu, Xin/0000-0001-6028-9692; | AC6: National Natural Science Foundation of China [51975431, 51575407] | AD6: National Natural Science Foundation of China(National Natural Science Foundation of China (NSFC)) | AE6: This research was supported by the National Natural Science Foundation of China (Nos. 51975431, 51575407). | AG6: 150 | AH6: 195 | AI6: 211 | AJ6: 161 | AK6: 1239 | AL6: ELSEVIER SCI LTD | AM6: London | AN6: 125 London Wall, London, ENGLAND | AO6: 1474-0346 | AP6: 1873-5320 | AR6: ADV ENG INFORM | AS6: Adv. Eng. Inform. | AT6: JAN | AU6: 2023 | AV6: 55 | BD6: 101876 | BE6: 10.1016/j.aei.2023.101876 | BF6: =HYPERLINK("http://dx.doi.org/10.1016/j.aei.2023.101876","http://dx.doi.org/10.1016/j.aei.2023.101876") -> http://dx.doi.org/10.1016/j.aei.2023.101876 | BH6: JAN 2023 | BI6: 18 | BJ6: Computer Science, Artificial Intelligence; Engineering, Multidisciplinary | BK6: Science Citation Index Expanded (SCI-EXPANDED) | BL6: Computer Science; Engineering | BM6: M7MU2 | BP6: Y | BQ6: N | BR6: 2025-11-04 | BS6: WOS:001032030200001 | BT6: =HYPERLINK("https%3A%2F%2Fwww.webofscience.com%2Fwos%2Fwoscc%2Ffull-record%2FWOS:001032030200001","View Full Record in Web of Science") -> View Full Record in Web of Science
A7: J | B7: Perno, M; Hvam, L; Haug, A | F7: Perno, Matteo; Hvam, Lars; Haug, Anders | I7: Implementation of digital twins in the process industry: A systematic literature review of enablers and barriers | J7: COMPUTERS IN INDUSTRY | M7: English | N7: Review | T7: Digital twin; Simulation; Process industry; Literature review; Barrier; Enabler | U7: BIG DATA; FUTURE; MODEL; SIMULATION; CHALLENGES; TRANSFORMATION; BLOCKCHAIN; DESIGN; ROLES | V7: Since the introduction of the concept of digital twins (DTs) in 2002, the number of practical applications in different industrial sectors has grown rapidly. Despite the hype surrounding this technology, companies face significant challenges upon deciding to implement DTs in their organizations due to the novelty of the concept. Furthermore, little research on DT has been conducted for the process industry, which may be explained by the high complexity of accurately representing and modeling the physics behind production processes. To consolidate the fragmented literature on the enabling factors and challenges in DT implementation in the process industry, this study organizes the existing studies on DTs with a focus on barriers and enablers. On this basis, this study contributes to the existing body of knowledge on DTs by organizing the DT literature and by proposing conceptual models describing enablers of and barriers to DT implementation, as well as their mutual relationships. (C) 2021 The Author(s). Published by Elsevier B.V. | W7: [Perno, Matteo; Hvam, Lars] Tech Univ Denmark, Dept Technol Management & Econ, Lyngby, Denmark; [Haug, Anders] Univ Southern Denmark, Dept Entrepreneurship & Relationship Management, Kolding, Denmark; [Perno, Matteo] Akademivej,Bldg 358, DK-2800 Lyngby, Denmark | X7: Technical University of Denmark; University of Southern Denmark | Y7: Perno, M (corresponding author), Tech Univ Denmark, Dept Technol Management & Econ, Lyngby, Denmark.;Perno, M (corresponding author), Akademivej,Bldg 358, DK-2800 Lyngby, Denmark. | Z7: matper@dtu.dk; lahv@dtu.dk; adg@sam.sdu.dk | AA7: ; Hvam, Lars/O-4313-2014; Haug, Anders/ABE-2706-2020 | AB7: Perno, Matteo/0000-0003-1165-7510; Haug, Anders/0000-0001-6173-6925 | AC7: Manufacturing Academy of Denmark (MADE); Department of Technology, Management and Economics at the Technical University of Denmark; Haldor Topsoe A/S | AD7: Manufacturing Academy of Denmark (MADE); Department of Technology, Management and Economics at the Technical University of Denmark; Haldor Topsoe A/S | AE7: This research was supported by the Manufacturing Academy of Denmark (MADE), the Department of Technology, Management and Economics at the Technical University of Denmark, and Haldor Topsoe A/S. | AG7: 107 | AH7: 162 | AI7: 183 | AJ7: 7 | AK7: 176 | AL7: ELSEVIER | AM7: AMSTERDAM | AN7: RADARWEG 29, 1043 NX AMSTERDAM, NETHERLANDS | AO7: 0166-3615 | AP7: 1872-6194 | AR7: COMPUT IND | AS7: Comput. Ind. | AT7: JAN | AU7: 2022 | AV7: 134 | BD7: 103558 | BE7: 10.1016/j.compind.2021.103558 | BF7: =HYPERLINK("http://dx.doi.org/10.1016/j.compind.2021.103558","http://dx.doi.org/10.1016/j.compind.2021.103558") -> http://dx.doi.org/10.1016/j.compind.2021.103558 | BI7: 16 | BJ7: Computer Science, Interdisciplinary Applications | BK7: Science Citation Index Expanded (SCI-EXPANDED) | BL7: Computer Science | BM7: 2R1VT | BO7: hybrid | BP7: Y | BQ7: N | BR7: 2025-11-04 | BS7: WOS:000820899900007 | BT7: =HYPERLINK("https%3A%2F%2Fwww.webofscience.com%2Fwos%2Fwoscc%2Ffull-record%2FWOS:000820899900007","View Full Record in Web of Science") -> View Full Record in Web of Science
A8: J | B8: Weil, C; Bibri, SE; Longchamp, R; Golay, F; Alahi, A | F8: Weil, Charlotte; Bibri, Simon Elias; Longchamp, Regis; Golay, Francois; Alahi, Alexandre | I8: Urban Digital Twin Challenges: A Systematic Review and Perspectives for Sustainable Smart Cities | J8: SUSTAINABLE CITIES AND SOCIETY | M8: English | N8: Review | T8: Urban digital twins; Digital twins; Sustainable smart cities; City management; City planning | U8: ARTIFICIAL-INTELLIGENCE; CITY; PLATFORM; IMPLEMENTATION; INTEGRATION; TECHNOLOGY; TOOLS | V8: Recent scientific and technological advancements have transformed the knowledge frontiers, giving rise to the next wave of disruptive technologies with deep impacts on urban society. An Urban Digital Twin (UDT) is a technology with great potential to transform the management and planning of the infrastructures and systems of sustainable smart cities towards environmental sustainability. However, despite the recent increase of research on UDTs due to its widespread diffusion much more recently, there is a lack of studies examining the existing bottlenecks to its implementation. To fill this gap, this study provides a systematic literature review on the key challenges and open issues pertaining to the implementation of an UDT. Results indicate 8 important categories of challenges related to (1) interoperability and semantics; (2) infrastructure, including storage, computation, network; (3) data acquisition and actuation; (4) data quality and harmonization; (5) modeling, simulation and decision-support; (6) data visualization and information display; (7) human and capital resources; and finally (8) governance, organizational and social issues. All topics are significantly raised in the literature, with most emphasis on issues pertaining to data and model semantics, missing data, data quality and modeling. The findings serve to inform practitioners about the bottlenecks delaying the implementation of UDTs. | W8: [Weil, Charlotte; Longchamp, Regis; Golay, Francois] Ecole Polytech Fed Lausanne, Sch Architecture Civil & Environm Engn, ENAC, EPFL, CH-1015 Lausanne, Switzerland; [Bibri, Simon Elias] Ecole Polytech Fed Lausanne, Sch Architecture Civil & Environm Engn, VITA, Visual Intelligence Transportat,ENAC,EPFL, CH-1015 Lausanne, Switzerland; [Alahi, Alexandre] Ecole Polytech fedeale Lausanne, VITA, Visual Intelligence Transportat, EPFL, CH-1015 Lausanne, Switzerland | X8: Swiss Federal Institutes of Technology Domain; Ecole Polytechnique Federale de Lausanne; Swiss Federal Institutes of Technology Domain; Ecole Polytechnique Federale de Lausanne; Swiss Federal Institutes of Technology Domain; Ecole Polytechnique Federale de Lausanne | Y8: Weil, C (corresponding author), Ecole Polytech Fed Lausanne, Sch Architecture Civil & Environm Engn, ENAC, EPFL, CH-1015 Lausanne, Switzerland. | Z8: charlotte.weil@epfl.ch | AA8: Alahi, Alexandre/AAP-5936-2021 | AB8: Golay, Francois/0000-0002-0683-0481; Weil, Charlotte/0000-0002-5423-1440; Bibri, Simon Elias/0009-0003-8559-6885 | AC8: Etat de Geneve, Departement du territoire (DT); European Union; [101034260] | AD8: Etat de Geneve, Departement du territoire (DT); European Union(European Union (EU)); | AE8: This work builds on an analysis conducted for the State of Geneva, mandated and supported financially by Etat de Geneve, Departement du territoire (DT) , Direction de l ' information du territoire through the FUSTIC association, the mandate was coordinated by Dr Frederic Dreyer.This work also received funding from the European Union' s Horizon 2020 research and innovation programme under the Marie Sklodowska-Curie grant agreement No 101034260. | AG8: 142 | AH8: 126 | AI8: 138 | AJ8: 45 | AK8: 167 | AL8: ELSEVIER | AM8: AMSTERDAM | AN8: RADARWEG 29, 1043 NX AMSTERDAM, NETHERLANDS | AO8: 2210-6707 | AP8: 2210-6715 | AR8: SUSTAIN CITIES SOC | AS8: Sust. Cities Soc. | AT8: DEC | AU8: 2023 | AV8: 99 | BD8: 104862 | BE8: 10.1016/j.scs.2023.104862 | BF8: =HYPERLINK("http://dx.doi.org/10.1016/j.scs.2023.104862","http://dx.doi.org/10.1016/j.scs.2023.104862") -> http://dx.doi.org/10.1016/j.scs.2023.104862 | BH8: AUG 2023 | BI8: 15 | BJ8: Construction & Building Technology; Green & Sustainable Science & Technology; Energy & Fuels | BK8: Science Citation Index Expanded (SCI-EXPANDED) | BL8: Construction & Building Technology; Science & Technology - Other Topics; Energy & Fuels | BM8: S2NG9 | BO8: Green Submitted | BP8: Y | BQ8: N | BR8: 2025-11-04 | BS8: WOS:001069583500001 | BT8: =HYPERLINK("https%3A%2F%2Fwww.webofscience.com%2Fwos%2Fwoscc%2Ffull-record%2FWOS:001069583500001","View Full Record in Web of Science") -> View Full Record in Web of Science
A9: J | B9: Lei, BY; Janssen, P; Stoter, J; Biljecki, F | F9: Lei, Binyu; Janssen, Patrick; Stoter, Jantien; Biljecki, Filip | I9: Challenges of urban digital twins: A systematic review and a Delphi expert survey | J9: AUTOMATION IN CONSTRUCTION | M9: English | N9: Review | T9: 3D city model; City information model; Virtual replica; Simulations; Urban planning | U9: FRAMEWORK; FUTURE; DESIGN; REFLECTIONS; LESSONS; CITIES; STATE; ART | V9: Many challenges to operate digital twins remain, hindering their design and implementation, and are rarely discussed. Furthermore, issues of social and legal nature are often overlooked. We identify the challenges of operating digital twins in the urban context through a bifurcated and multi-dimensional approach: a systematic literature review and an expert survey. The review organises the identified challenges across technical and non-technical dimensions. As the topic is novel, the corpus is rather small and lacking the contextualisation of challenges. Thus, we complement it with a survey based on the Delphi method, involving a diverse panel of domain experts covering academia, industry and government organisations. Combining the results, we identify 14 technical and 9 non-technical challenges and map them to phases of the digital twin's life cycle. The most severe challenges appear to be related to interoperability (e.g. disparate semantic standards) and practical value (e.g. lack of business models). | W9: [Lei, Binyu; Janssen, Patrick; Biljecki, Filip] Natl Univ Singapore, Dept Architecture, Singapore, Singapore; [Stoter, Jantien] Delft Univ Technol, 3D Geoinformat Grp, Delft, Netherlands; [Biljecki, Filip] Natl Univ Singapore, Dept Real Estate, Singapore, Singapore; [Biljecki, Filip] Natl Univ Singapore, Dept Architecture, 4 Architecture Dr, Singapore 117566, Singapore | X9: National University of Singapore; Delft University of Technology; National University of Singapore; National University of Singapore | Y9: Biljecki, F (corresponding author), Natl Univ Singapore, Dept Architecture, 4 Architecture Dr, Singapore 117566, Singapore. | Z9: filip@nus.edu.sg | AA9: Lei, Binyu/JMC-2680-2023; Biljecki, Filip/B-9829-2013; Janssen, Patrick/J-6019-2015 | AB9: Lei, Binyu/0000-0002-8501-3104; Stoter, Jantien/0000-0002-1393-7279 | AC9: National University of Singapore; Singapore Ministry of Education Academic Research Fund Tier 1; [R-295-000-171-133] | AD9: National University of Singapore(National University of Singapore); Singapore Ministry of Education Academic Research Fund Tier 1(Ministry of Education, Singapore); | AE9: The Institutional Review Board of the National University of Singa-pore has reviewed and approved the ethical aspects of this research (Reference Code: NUS-IRB-2022-87) . We are grateful to all expert panellists for their time and patience to participate in our Delphi survey and providing valuable responses for this research. We particularly wish to thank the European Spatial Data Research network (EuroSDR) and the 3D Information Management (3DIM) Domain Working Group of the Open Geospatial Consortium (OGC) for their kind efforts to distribute our survey. We thank Dr Claire Ellul (University College London) for her support and discussions related to the survey. We thank the members of the NUS Urban Analytics Lab for the discussions, in particular, Dr Pengyuan Liu for the constructive comments on the earlyversions of the paper. This research is part of the projects (i) Large-scale 3D Geospatial Data for Urban Analytics, which is supported by the National University of Singapore under the Start Up Grant R-295-000-171-133; and (ii) Multi-scale Digital Twins for the Urban Environment: From Heartbeats to Cities, which is supported by the Singapore Ministry of Education Academic Research Fund Tier 1. | AG9: 125 | AH9: 101 | AI9: 107 | AJ9: 25 | AK9: 201 | AL9: ELSEVIER | AM9: AMSTERDAM | AN9: RADARWEG 29, 1043 NX AMSTERDAM, NETHERLANDS | AO9: 0926-5805 | AP9: 1872-7891 | AR9: AUTOMAT CONSTR | AS9: Autom. Constr. | AT9: MAR | AU9: 2023 | AV9: 147 | BD9: 104716 | BE9: 10.1016/j.autcon.2022.104716 | BF9: =HYPERLINK("http://dx.doi.org/10.1016/j.autcon.2022.104716","http://dx.doi.org/10.1016/j.autcon.2022.104716") -> http://dx.doi.org/10.1016/j.autcon.2022.104716 | BH9: JAN 2023 | BI9: 15 | BJ9: Construction & Building Technology; Engineering, Civil | BK9: Science Citation Index Expanded (SCI-EXPANDED) | BL9: Construction & Building Technology; Engineering | BM9: 8I1UV | BO9: hybrid | BP9: Y | BQ9: N | BR9: 2025-11-04 | BS9: WOS:000921513800001 | BT9: =HYPERLINK("https%3A%2F%2Fwww.webofscience.com%2Fwos%2Fwoscc%2Ffull-record%2FWOS:000921513800001","View Full Record in Web of Science") -> View Full Record in Web of Science
A10: J | B10: Bibri, SE; Huang, J; Jagatheesaperumal, SK; Krogstie, J | F10: Bibri, Simon Elias; Huang, Jeffrey; Jagatheesaperumal, Senthil Kumar; Krogstie, John | I10: The synergistic interplay of artificial intelligence and digital twin in environmentally planning sustainable smart cities: A comprehensive systematic review | J10: ENVIRONMENTAL SCIENCE AND ECOTECHNOLOGY | M10: English | N10: Review | T10: Sustainable smart cities; Arti ficial intelligence; Arti ficial intelligence of things; Urban digital twin; Data -driven urban planning; Environmental planning; Environmental sustainability | U10: OF-THE-ART; BIG DATA; CHALLENGES; PLATFORM; THINGS; TOOLS; OPPORTUNITIES; COMPLEXITY; METAVERSE; INTERNET | V10: The dynamic landscape of sustainable smart cities is witnessing a signi ficant transformation due to the integration of emerging computational technologies and innovative models. These advancements are reshaping data -driven planning strategies, practices, and approaches, thereby facilitating the achievement of environmental sustainability goals. This transformative wave signals a fundamental shift d marked by the synergistic operation of arti ficial intelligence (AI), arti ficial intelligence of things (AIoT), and urban digital twin (UDT) technologies. While previous research has largely explored urban AI, urban AIoT, and UDT in isolation, a signi ficant knowledge gap exists regarding their synergistic interplay, collaborative integration, and collective impact on data -driven environmental planning in the dynamic context of sustainable smart cities. To address this gap, this study conducts a comprehensive systematic review to uncover the intricate interactions among these interconnected technologies, models, and domains while elucidating the nuanced dynamics and untapped synergies in the complex ecosystem of sustainable smart cities. Central to this study are four guiding research questions: 1. What theoretical and practical foundations underpin the convergence of AI, AIoT, UDT, data -driven planning, and environmental sustainability in sustainable smart cities, and how can these components be synthesized into a novel comprehensive framework? 2. How does integrating AI and AIoT reshape the landscape of datadriven planning to improve the environmental performance of sustainable smart cities? 3. How can AI and AIoT augment the capabilities of UDT to enhance data -driven environmental planning processes in sustainable smart cities? 4. What challenges and barriers arise in integrating and implementing AI, AIoT, and UDT in data -driven environmental urban planning, and what strategies can be devised to surmount or mitigate them? Methodologically, this study involves a rigorous analysis and synthesis of studies published between January 2019 and December 2023, comprising an extensive body of literature totaling 185 studies. The findings of this study surpass mere interdisciplinary theoretical enrichment, offering valuable insights into the transformative potential of integrating AI, AIoT, and UDT technologies to advance sustainable urban development practices. By enhancing data -driven environmental planning processes, these integrated technologies and models offer innovative solutions to address complex environmental challenges. However, this endeavor is fraught with formidable challenges and complexities that require careful navigation and mitigation to achieve desired outcomes. This study serves as a comprehensive reference guide, spurring groundbreaking research endeavors, stimulating practical implementations, informing strategic initiatives, and shaping policy formulations in sustainable urban development. These insights have profound implications for researchers, practitioners, and policymakers, providing a roadmap for fostering resiliently designed, technologically advanced, and environmentally conscious urban environments. (c) 2024 The Author(s). Published by Elsevier B.V. on behalf of Chinese Society for Environmental Sciences, Harbin Institute of Technology, Chinese Research Academy of Environmental Sciences. This is an open access article under the CC BY license (http://creativecommons.org/licenses/by/4.0/). | W10: [Bibri, Simon Elias; Huang, Jeffrey] Swiss Fed Inst Technol Lausanne EPFL, Inst Comp & Commun Sci IINFCOM, Sch Architecture Civil & Environm Engn ENAC, Media & Design Lab LDM, CH-1015 Lausanne, Switzerland; [Jagatheesaperumal, Senthil Kumar] Mepco Schlenk Engn Coll, Dept Elect & Commun Engn, Sivakasi 626005, Tamilnadu, India; [Krogstie, John] Norwegian Univ Sci & Technol NTNU, Dept Comp Sci, Trondheim, Norway | X10: Swiss Federal Institutes of Technology Domain; Ecole Polytechnique Federale de Lausanne; Mepco Schlenk Engineering College; Norwegian University of Science & Technology (NTNU) | Y10: Bibri, SE (corresponding author), Swiss Fed Inst Technol Lausanne EPFL, Inst Comp & Commun Sci IINFCOM, Sch Architecture Civil & Environm Engn ENAC, Media & Design Lab LDM, CH-1015 Lausanne, Switzerland. | Z10: simon.bibri@epfl.ch | AA10: Jagatheesaperumal, Senthil Kumar/S-9258-2019; Jagatheesaperumal, Senthil Kumar/S-9258-2019; Krogstie, John/NBX-4350-2025 | AB10: Jagatheesaperumal, Senthil Kumar/0000-0002-9516-0327; Jagatheesaperumal, Senthil Kumar/0000-0002-9516-0327; Krogstie, John/0000-0003-4830-1876 | AG10: 208 | AH10: 68 | AI10: 78 | AJ10: 49 | AK10: 137 | AL10: ELSEVIER | AM10: AMSTERDAM | AN10: RADARWEG 29, 1043 NX AMSTERDAM, NETHERLANDS | AO10: 2666-4984 | AR10: ENVIRON SCI ECOTECH | AS10: Env. Sci. Ecotechnol. | AT10: JUL | AU10: 2024 | AV10: 20 | BD10: 100433 | BE10: 10.1016/j.ese.2024.100433 | BF10: =HYPERLINK("http://dx.doi.org/10.1016/j.ese.2024.100433","http://dx.doi.org/10.1016/j.ese.2024.100433") -> http://dx.doi.org/10.1016/j.ese.2024.100433 | BH10: MAY 2024 | BI10: 26 | BJ10: Green & Sustainable Science & Technology; Environmental Sciences | BK10: Science Citation Index Expanded (SCI-EXPANDED) | BL10: Science & Technology - Other Topics; Environmental Sciences & Ecology | BM10: UA0B0 | BN10: 38831974 | BO10: Green Submitted, gold | BP10: Y | BQ10: N | BR10: 2025-11-04 | BS10: WOS:001245213400001 | BT10: =HYPERLINK("https%3A%2F%2Fwww.webofscience.com%2Fwos%2Fwoscc%2Ffull-record%2FWOS:001245213400001","View Full Record in Web of Science") -> View Full Record in Web of Science

Sheet 1_20251104.wos.table
A1: ID | B1: DOI | C1: Title | D1: Databases
A2: DT.DBQ1.01 | B2: ='1_20251104.wos'!BF2 -> http://dx.doi.org/10.1016/j.cirpj.2020.02.002 | C2: ='1_20251104.wos'!I2 -> Characterising the Digital Twin: A systematic literature review
A3: DT.DBQ1.02 | B3: ='1_20251104.wos'!BF3 -> http://dx.doi.org/10.1016/j.compind.2021.103469 | C3: ='1_20251104.wos'!I3 -> Digital twin paradigm: A systematic literature review
A4: DT.DBQ1.03 | B4: ='1_20251104.wos'!BF4 -> http://dx.doi.org/10.1109/ACCESS.2021.3060863 | C4: ='1_20251104.wos'!I4 -> The Role of AI, Machine Learning, and Big Data in Digital Twinning: A Systematic Literature Review, Challenges, and Opportunities
A5: DT.DBQ1.04 | B5: ='1_20251104.wos'!BF5 -> http://dx.doi.org/10.1016/j.infsof.2022.107008 | C5: ='1_20251104.wos'!I5 -> Predictive maintenance using digital twins: A systematic literature review
A6: DT.DBQ1.05 | B6: ='1_20251104.wos'!BF6 -> http://dx.doi.org/10.1016/j.aei.2023.101876 | C6: ='1_20251104.wos'!I6 -> A systematic review of digital twin about physical entities, virtual models, twin data, and applications
A7: DT.DBQ1.06 | B7: ='1_20251104.wos'!BF7 -> http://dx.doi.org/10.1016/j.compind.2021.103558 | C7: ='1_20251104.wos'!I7 -> Implementation of digital twins in the process industry: A systematic literature review of enablers and barriers
A8: DT.DBQ1.07 | B8: ='1_20251104.wos'!BF8 -> http://dx.doi.org/10.1016/j.scs.2023.104862 | C8: ='1_20251104.wos'!I8 -> Urban Digital Twin Challenges: A Systematic Review and Perspectives for Sustainable Smart Cities
A9: DT.DBQ1.08 | B9: ='1_20251104.wos'!BF9 -> http://dx.doi.org/10.1016/j.autcon.2022.104716 | C9: ='1_20251104.wos'!I9 -> Challenges of urban digital twins: A systematic review and a Delphi expert survey
A10: DT.DBQ1.09 | B10: ='1_20251104.wos'!BF10 -> http://dx.doi.org/10.1016/j.ese.2024.100433 | C10: ='1_20251104.wos'!I10 -> The synergistic interplay of artificial intelligence and digital twin in environmentally planning sustainable smart cities: A comprehensive systematic review
C11: ='1_20251104.wos'!I11

Sheet 1_20251104.wos_results
A1: Database | B1: Num | C1: ='1_20251104.wos.table'!A2 -> DT.DBQ1.01 | D1: ='1_20251104.wos.table'!A3 -> DT.DBQ1.02 | E1: ='1_20251104.wos.table'!A4 -> DT.DBQ1.03 | F1: ='1_20251104.wos.table'!A5 -> DT.DBQ1.04 | G1: ='1_20251104.wos.table'!A6 -> DT.DBQ1.05 | H1: ='1_20251104.wos.table'!A7 -> DT.DBQ1.06 | I1: ='1_20251104.wos.table'!A8 -> DT.DBQ1.07 | J1: ='1_20251104.wos.table'!A9 -> DT.DBQ1.08 | K1: ='1_20251104.wos.table'!A10 -> DT.DBQ1.09 | L1: Total | M1: Percentual | N1: Percentual cumulativo | O1: Percentual
A2: Scopus | B2: 1 | D2: 1 | E2: 1 | F2: 1 | G2: 1 | H2: 1 | I2: 1 | K2: 1 | L2: =SUM(C2:K2) -> 7 | M2: =L2/$L$18 -> 0.18421053 | N2: =M2 -> 0.18421053 | O2: =1/B17 -> 0.0625
A3: ScienceDirect | B3: =B2+1 -> 2 | D3: 1 | E3: 1 | F3: 1 | I3: 1 | K3: 1 | L3: =SUM(C3:K3) -> 5 | M3: =L3/$L$18 -> 0.13157895 | N3: =N2+M3 -> 0.31578947 | O3: =O2+1/$B$17 -> 0.125
A4: IEEE Xplore (IEEE, IET) | B4: =B3+1 -> 3 | E4: 1 | F4: 1 | G4: 1 | H4: 1 | L4: =SUM(C4:K4) -> 4 | M4: =L4/$L$18 -> 0.10526316 | N4: =N3+M4 -> 0.42105263 | O4: =O3+1/$B$17 -> 0.1875
A5: ACM digital library | B5: =B4+1 -> 4 | E5: 1 | F5: 1 | H5: 1 | L5: =SUM(C5:K5) -> 3 | M5: =L5/$L$18 -> 0.078947368 | N5: =N4+M5 -> 0.5 | O5: =O4+1/$B$17 -> 0.25
A6: Wiley online library | B6: =B5+1 -> 5 | E6: 1 | F6: 1 | G6: 1 | L6: =SUM(C6:K6) -> 3 | M6: =L6/$L$18 -> 0.078947368 | N6: =N5+M6 -> 0.57894737 | O6: =O5+1/$B$17 -> 0.3125
A7: Web of Science | B7: =B6+1 -> 6 | H7: 1 | I7: 1 | K7: 1 | L7: =SUM(C7:K7) -> 3 | M7: =L7/$L$18 -> 0.078947368 | N7: =N6+M7 -> 0.65789474 | O7: =O6+1/$B$17 -> 0.375
A8: SpringerLink (Springer) | B8: =B7+1 -> 7 | E8: 1 | F8: 1 | L8: =SUM(C8:K8) -> 2 | M8: =L8/$L$18 -> 0.052631579 | N8: =N7+M8 -> 0.71052632 | O8: =O7+1/$B$17 -> 0.4375
A9: Taylor & Francis online | B9: =B8+1 -> 8 | E9: 1 | F9: 1 | L9: =SUM(C9:K9) -> 2 | M9: =L9/$L$18 -> 0.052631579 | N9: =N8+M9 -> 0.76315789 | O9: =O8+1/$B$17 -> 0.5
A10: Google Scholar | B10: =B9+1 -> 9 | G10: 1 | I10: 1 | L10: =SUM(C10:K10) -> 2 | M10: =L10/$L$18 -> 0.052631579 | N10: =N9+M10 -> 0.81578947 | O10: =O9+1/$B$17 -> 0.5625
A11: CIRP | B11: =B10+1 -> 10 | C11: 1 | L11: =SUM(C11:K11) -> 1 | M11: =L11/$L$18 -> 0.026315789 | N11: =N10+M11 -> 0.84210526 | O11: =O10+1/$B$17 -> 0.625
A12: IFAC-Papers Online 7 | B12: =B11+1 -> 11 | C12: 1 | L12: =SUM(C12:K12) -> 1 | M12: =L12/$L$18 -> 0.026315789 | N12: =N11+M12 -> 0.86842105 | O12: =O11+1/$B$17 -> 0.6875
A13: Procedia Manufacturing | B13: =B12+1 -> 12 | C13: 1 | L13: =SUM(C13:K13) -> 1 | M13: =L13/$L$18 -> 0.026315789 | N13: =N12+M13 -> 0.89473684 | O13: =O12+1/$B$17 -> 0.75
A14: International Journal of Advanced Manufacturing Technology | B14: =B13+1 -> 13 | C14: 1 | L14: =SUM(C14:K14) -> 1 | M14: =L14/$L$18 -> 0.026315789 | N14: =N13+M14 -> 0.92105263 | O14: =O13+1/$B$17 -> 0.8125
A15: Journal of Ambient Intelligence and Humanoid Computing | B15: =B14+1 -> 14 | C15: 1 | L15: =SUM(C15:K15) -> 1 | M15: =L15/$L$18 -> 0.026315789 | N15: =N14+M15 -> 0.94736842 | O15: =O14+1/$B$17 -> 0.875
A16: Hindawi | B16: =B15+1 -> 15 | E16: 1 | L16: =SUM(C16:K16) -> 1 | M16: =L16/$L$18 -> 0.026315789 | N16: =N15+M16 -> 0.97368421 | O16: =O15+1/$B$17 -> 0.9375
A17: IGI-Global | B17: =B16+1 -> 16 | E17: 1 | L17: =SUM(C17:K17) -> 1 | M17: =L17/$L$18 -> 0.026315789 | N17: =N16+M17 -> 1 | O17: =O16+1/$B$17 -> 1
A18: Total | C18: =SUM(C2:C17) -> 5 | D18: =SUM(D2:D17) -> 2 | E18: =SUM(E2:E17) -> 9 | F18: =SUM(F2:F17) -> 7 | G18: =SUM(G2:G17) -> 4 | H18: =SUM(H2:H17) -> 4 | I18: =SUM(I2:I17) -> 4 | J18: =SUM(J2:J17) -> 0 | ... M18: =SUM(M2:M17) -> 1

Sheet scopus_export_Nov 16-2025_filte
A1: Key | B1: Item Type | C1: Publication Year | D1: Author | E1: Title | F1: Publication Title | G1: ISBN | H1: ISSN | I1: DOI | J1: Url | K1: Abstract Note | L1: Date | M1: Date Added | N1: Date Modified | O1: Access Date | P1: Pages | Q1: Num Pages | R1: Issue | S1: Volume | T1: Number Of Volumes | U1: Journal Abbreviation | V1: Short Title | W1: Series | X1: Series Number | Y1: Series Text | Z1: Series Title | AA1: Publisher | AB1: Place | AC1: Language | AD1: Rights | AE1: Type | AF1: Archive | AG1: Archive Location | AH1: Library Catalog | AI1: Call Number | AJ1: Extra | AK1: Notes | AL1: File Attachments | AM1: Link Attachments | AN1: Manual Tags | AO1: Automatic Tags | AP1: Editor | AQ1: Series Editor | AR1: Translator | AS1: Contributor | AT1: Attorney Agent | AU1: Book Author | AV1: Cast Member | AW1: Commenter | AX1: Composer | AY1: Cosponsor | AZ1: Counsel | BA1: Interviewer | BB1: Producer | BC1: Recipient | BD1: Reviewed Author | BE1: Scriptwriter | BF1: Words By | BG1: Guest | BH1: Number | BI1: Edition | BJ1: Running Time | BK1: Scale | BL1: Medium | BM1: Artwork Size | BN1: Filing Date | BO1: Application Number | BP1: Assignee | BQ1: Issuing Authority | BR1: Country | BS1: Meeting Name | BT1: Conference Name | BU1: Court | BV1: References | BW1: Reporter | BX1: Legal Status | BY1: Priority Numbers | BZ1: Programming Language | CA1: Version | CB1: System | CC1: Code | CD1: Code Number | CE1: Section | CF1: Session | CG1: Committee | CH1: History | CI1: Legislative Body
A2: Y3PA3JS8 | B2: journalArticle | C2: 2024 | D2: Aghazadeh Ardebili, A.; Zappatore, M.; Ramadan, A.I.H.A.; Longo, A.; Ficarella, A. | E2: Digital Twins of smart energy systems: a systematic literature review on enablers, design, management and computational challenges | F2: Energy Informatics | H2: 25208942 (ISSN) | I2: 10.1186/s42162-024-00385-5 | J2: https://www.scopus.com/inward/record.uri?eid=2-s2.0-85205923870&doi=10.1186%2Fs42162-024-00385-5&partnerID=40&md5=806c3f02ba8c9f382702f93b30376aed | K2: Background: Energy systems, as critical infrastructures (CI), constitute Cyber-Physical-Social Systems (CPSS). Due to their inherent complexity and the importance of service continuity of CIs, digitization in this context encounters significant practical challenges. Digital Twins (DT) have emerged over the recent years as a promising solution for managing CPSSs by facilitating real-time interaction, synchronization, and control of physical assets. The selection of an appropriate architectural framework is crucial in constructing a DT, to ensure integration of enabling technologies and data from diverse sources. Objectives: This study proposes a Systematic Literature Review (SLR) to examine technological enablers, design choices, management strategies and Computational Challenges of DTs in Smart Energy Systems (SES) by also analyzing existing architectures and identifying key components. Methods: The SLR follows a rigorous workflow exploiting a multi-database search with predefined eligibility criteria, accompanied by advanced searching techniques, such as manual screening of results and a documented search strategy, in order to ensure its comprehensiveness and reliability, More specifically, research questions are first defined and then submitted as queries to scientific digital libraries (i.e., IEEE Xplore, Scopus, and WoS) selected due to their coverage and reliability (Google Scholar was excluded for the presence of grey literature and non-peer-reviewed material). Then, inclusion and exclusion criteria are established to filter the results and shortlist the significant publications. Subsequently, relevant data are extracted, summarized, and categorized in order to identify common themes, existing gaps, and future research directions, with the aim of providing a comprehensive overview of the current state of DTs for SESs. Results: From the proposed DT-based solutions described in the selected publications, the adopted architectures are examined and categorized depending on their logical building blocks, microservices, enabling technologies, human–machine interfaces (HMI), artificial intelligence and machine learning (AI/ML) implementations, data flow and data persistence choices, and Internet-of-Things (IoT) components involved. Additionally, the integration of edge-cloud computing and IoT technologies in literature are studied and discussed. Finally, gaps, opportunities, future study lines, and challenges of implementing DTs are thoroughly addressed. The results achieved also pave the way for a forthcoming design pattern catalog for DTs in CPSSs capable of supporting the engineering and research communities, by offering practical insights on implementation and integration aspects. Conclusion: The proposed SLR provides a valuable resource for designing and implementing DTs of CPSSs in general and of SESs in particular. Furthermore, it highlights the potential benefits of adopting DTs to manage complex energy systems and it identifies areas for future research. © 2024 Elsevier B.V., All rights reserved. | L2: 2024 | M2: 45977.672 | N2: 45981.516 | R2: 1 | S2: 7 | U2: Energy. Inform. | AC2: English | AF2: Scopus | AJ2: Publisher: Springer Nature | AN2: Reviews; Network security; Digital Twin; Bibliographies; Systems architecture; Cyber-physical systems; Interoperability; Energy; Cybe-physical systems; Complex system; Cybe-physical-social system; Cyber physicals; Cyber-Physical System; Cyber-Physical-Social System; Edge clouds; Edge-cloud continuum; Edge-Cloud Continuum; Empowerment of personnel; Energy internet; Energy internet-of-thing; Energy IoT; Failure rate; Fault tree analysis; Foil bearings; Gas bearings; Graph structures; Internet of energy; Magnetic couplings; Piston rings; Railroad bearings; Ring springs; Rotating disks; Screws; SGML; Shear walls; Smart energy system; Smart energy systems; Social systems; System architecture; Variable speed drives; Voltage scaling; included
A3: JMC9E8SA | B3: journalArticle | C3: 2025 | D3: Antonesi, G.; Cioara, T.; Anghel, I.; Michalakopoulos, V.; Sarmas, E.; Toderean, L. | E3: A systematic review of transformers and large language models in the energy sector: towards agentic digital twins | F3: Applied Energy | H3: 18729118 (ISSN); 03062619 (ISSN) | I3: 10.1016/j.apenergy.2025.126670 | J3: https://www.scopus.com/inward/record.uri?eid=2-s2.0-105013772709&doi=10.1016%2Fj.apenergy.2025.126670&partnerID=40&md5=c1cad25a7dc752b2dbd6cb8ee9706b33 | K3: Artificial intelligence (AI) has long promised to improve energy management in smart grids by enhancing situational awareness and supporting more effective decision-making. While traditional machine learning has demonstrated notable results in forecasting and optimization, it often struggles with generalization, situational awareness, and heterogeneous data integration. Recent advances in Transformer architecture, including Large Language Models (LLMs) and Foundation Models (FMs) can significantly improve the ability to model complex temporal and contextual relationships, as well as in multi-modal data fusion which is valuable for most AI applications in the energy sector. In this review, we synthesize the rapidly expanding field of AI applications in the energy domain, with a focus on Transformer Models (TMs) and LLMs, which have shown growing relevance. We examine the architectural foundations, domain-specific adaptations and practical implementations of TMs across various forecasting and grid management tasks. We then explore the emerging role of LLMs in the field: adaptation and fine tuning for the energy sector, the type of tasks they are suited for, and the new challenges they introduce. Along the way, we highlight practical implementations, innovations, and areas where the research frontier is rapidly expanding. These recent developments reviewed underscore a broader trend: Generative AI (GenAI) is beginning to augment decision-making not only in high-level planning but also in day-to-day operations, from forecasting and grid balancing to workforce training and asset onboarding. While FMs hold promises, we found limited evidence of their concrete application in energy domain to date. Therefore we introduce the concept of the Agentic Digital Twin, a next-generation model that integrates FMs to bring multi-modal situational awareness, autonomy, proactivity, and social interaction into digital twin-based energy management systems. We present the transformational impact of FMs to each phase of a digital twin and identify the open challenges that need to be addressed for their efficient and effective integration. © 2025 Elsevier B.V., All rights reserved. | L3: 2025 | M3: 45977.672 | N3: 45981.512 | S3: 401 | U3: Appl. Energy | AC3: English | AF3: Scopus | AJ3: Publisher: Elsevier Ltd | AN3: Artificial intelligence; machine learning; literature review; Large language models; Data integration; Digital twin; Agentic digital twins; Energy sector; Foundation models; GenAI; Generative AI; Smart grid; Transformers; Forecasting; Decision making; Agentic digital twin; Behavioral research; digitization; Electric transformers; energy management; Energy policy; Generative artificial intelligence; Language model; Large language model; Modal analysis; numerical model; Situational awareness; smart grid; Smart power grids; Transformer; included
A4: URBJYMAX | B4: conferencePaper | C4: 2023 | D4: Arin, I.A.; Meyliana, n.; Warnars, H.L.H.S.; Murad, D.F. | E4: A Systematic Literature Review of Recent Trends and Challenges in Digital Twin Implementation | F4: Int. Conf. ICT for Smart Soc., ICISS - Proceeding | G4: 9798350339543 (ISBN) | I4: 10.1109/ICISS59129.2023.10291219 | J4: https://www.scopus.com/inward/record.uri?eid=2-s2.0-85177460118&doi=10.1109%2FICISS59129.2023.10291219&partnerID=40&md5=a6bc6d3e07f2b2bddf90df9ceb1c59fd | K4: This paper reviews the latest trends and challenges in implementing digital twin technology. A digital twin is a tool used in various industries to improve efficiency, optimize processes, and enable advanced analysis. The review involved searching major research databases and search engines for articles published between 2018 and 2023. The findings reveal several important trends, including the development of different types of digital twin dimensions, each with its own advantages and limitations. The benefits of digital twin implementation include improved decision-making, increased productivity, and operational efficiency. However, there are challenges, such as data integration, security and privacy concerns, a lack of standardization, and the need for experts to effectively design and operate digital twins. The implications of these trends and challenges are discussed regarding their impact on the successful adoption and implementation of digital twin technology. The review also highlights the need to address these challenges and explore new approaches for maximizing the benefits of digital twin technology. Overall, this comprehensive review is a valuable resource for researchers, practitioners, and organizations seeking to understand the current landscape, identify areas for improvement, and make informed decisions when implementing digital twin technology. © 2023 Elsevier B.V., All rights reserved. | L4: 2023 | M4: 45977.672 | N4: 45981.511 | AA4: Institute of Electrical and Electronics Engineers Inc. | AC4: English | AF4: Scopus | AJ4: Journal Abbreviation: Int. Conf. ICT for Smart Soc., ICISS - Proceeding | AN4: digital twin; Systematic literature review; Data integration; systematic literature review; Decision making; Decisions makings; Challenge; Search engines; Efficiency; challenges; Advanced analysis; implementation; Implementation; Increased productivity; Operational efficiencies; Recent trends; Research database; Trend; trends; included
A5: 5DW7CSCF | B5: journalArticle | C5: 2025 | D5: Arin, I.A.; Murad, D.F.; Warnars, H.L.H.S. | E5: Digital Twin Integration in Field Service Management: A Hybrid Systematic Literature Review and Bibliometric Analysis (2017-2024) | F5: International Journal of Sustainable Development and Planning | H5: 17437601 (ISSN); 1743761X (ISSN) | I5: 10.18280/ijsdp.200801 | J5: https://www.scopus.com/inward/record.uri?eid=2-s2.0-105018889828&doi=10.18280%2Fijsdp.200801&partnerID=40&md5=a6858ecf572b9ea40e2bd53c60298ce0 | K5: Field Service Management (FSM) is undergoing a significant transformation through digital twin technology integration. This study employs a hybrid methodological framework combining systematic literature review (SLR) and bibliometric analysis to examine 166 scholarly publications from 2017-2024. Our findings reveal: (1) a 23.7% compound annual growth rate in FSM research with distinct evolution phases from basic digitization to intelligent integration; (2) digital twin technology emerging as the most transformative innovation in FSM, enabling unprecedented 99.9% network uptime in telecommunications infrastructure; (3) a three-stage maturity model for digital twin implementation (virtual modeling, real-time synchronization, predictive optimization); and (4) implementation barriers including technological integration challenges (38.5%) and organizational resistance (32.4%). The research identifies artificial intelligence integration (42.8%) and autonomous service delivery (35.6%) as dominant future directions for digital twin applications in FSM. This study contributes to information systems theory by mapping the intellectual structure of FSM knowledge and offering the first comprehensive digital twin integration framework for FSM implementation, while providing practitioners with evidence-based strategies for achieving quantifiable operational improvements, particularly in telecommunications infrastructure management. © 2025 Elsevier B.V., All rights reserved. | L5: 2025 | M5: 45977.672 | N5: 45981.511 | P5: 3155-3169 | R5: 8 | S5: 20 | U5: Int. J. Sustainable Dev. Plann. | AC5: English | AF5: Scopus | AJ5: Publisher: International Information and Engineering Technology Association | AN5: artificial intelligence; innovation; literature review; digitization; bibliometric analysis; digital twin technology; field service management (FSM); growth rate; infrastructure; systematic literature review (SLR); technological change; technology integration; telecommunication; telecommunication infrastructure; included
A6: ZMTL8ZKG | B6: journalArticle | C6: 2025 | D6: Ba, L.; Tangour, F.; El Abbassi, I.; Absi, R. | E6: Analysis of Digital Twin Applications in Energy Efficiency: A Systematic Review | F6: Sustainability (Switzerland) | H6: 20711050 (ISSN) | I6: 10.3390/su17083560 | J6: https://www.scopus.com/inward/record.uri?eid=2-s2.0-105003656265&doi=10.3390%2Fsu17083560&partnerID=40&md5=15880fe7a56c0315846422e00798a2f4 | K6: Digital Twin (DT) technology is emerging as a powerful tool for optimizing energy efficiency and industrial sustainability. By creating virtual replicas of physical systems, DTs enable real-time monitoring, predictive maintenance, and resource optimization, offering new opportunities to meet growing energy demands. Despite its potential, the comprehension of DT technology’s applications, benefits, and challenges remains limited. This systematic review explores the role of Digital Twins in energy efficiency across various industries. A structured literature search was conducted in IEEE Xplore, Elsevier, Springer, MDPI, and Google Scholar, following PRISMA 2020 guidelines. After applying the predefined inclusion criteria, 50 studies were selected for in-depth analysis. The findings highlight that DT implementation can lead to energy savings of up to 30%, reduce operational costs, and improve predictive maintenance strategies. Their impact is particularly notable in smart buildings, manufacturing, and industrial processes, where real-time data analytics contribute to better energy management. However, significant barriers remain, including high implementation costs, data security risks, and the complexity of integrating DTs with existing infrastructures. By synthesizing the current research, this review underscores the transformative potential of Digital Twins while identifying key challenges that need to be addressed for their wider adoption. Future efforts should focus on developing standardized methodologies, reducing implementation costs, and enhancing cybersecurity measures to maximize their benefits in energy efficiency and sustainability. © 2025 Elsevier B.V., All rights reserved. | L6: 2025 | M6: 45977.672 | N6: 45981.509 | R6: 8 | S6: 17 | U6: Sustainability | AC6: English | AF6: Scopus | AJ6: Publisher: Multidisciplinary Digital Publishing Institute (MDPI) | AN6: energy efficiency; sustainability; literature review; Industry 4.0; Digital Twin; predictive maintenance; digitization; maintenance; smart buildings; energy storage; included
A7: EDVYUZNA | B7: journalArticle | C7: 2025 | D7: Bae, C.; Choi, E.; Lee, S. | E7: Technologies, Applications, and Challenges of Digital Twin Across Industries: A Systematic Review of the State-of-the-Art Literature | F7: IEEE Access | H7: 21693536 (ISSN) | I7: 10.1109/ACCESS.2025.3601615 | J7: https://www.scopus.com/inward/record.uri?eid=2-s2.0-105013996327&doi=10.1109%2FACCESS.2025.3601615&partnerID=40&md5=77d1ad982062f63bd474c7c3f19c5387 | K7: Digital twins can be defined as a virtual representation of a physical object that can replicate its behavior in a virtual environment. This concept involves the integration of three distinct components: the physical space, the virtual space, and the communication between these two spaces. Digital twins are recognized as one of the key driving forces in various industries, and a comprehensive understanding is necessary to utilize them. A thorough review of the advantages and disadvantages of digital twins, including their value, characteristics, applications, and challenges, is essential to analyze their growth potential and investment value. This paper comprehensively reviews the digital twin applications being studied across industries. To this end, we propose three research questions and address them through a structured literature review. First, we examine the core technologies of digital twins and find that they form an integrated framework combining modeling, sensing, and real-time data processing. Second, we analyze their adoption across industries and observe widespread use in aerospace and aeronautics, manufacturing, healthcare, energy, and urban systems with domain-specific objectives. Third, we explore life-cycle applications and identify digital twins as enablers of continuity from design to operation and evolution. These findings offer a broad perspective on the current state and future potential of digital twin applications. © 2025 Elsevier B.V., All rights reserved. | L7: 2025 | M7: 45977.672 | N7: 45981.508 | P7: 152843-152869 | S7: 13 | U7: IEEE Access | AC7: English | AF7: Scopus | AJ7: Publisher: Institute of Electrical and Electronics Engineers Inc. | AN7: Industry 4.0; Digital twin; Life cycle; Systematic Review; Virtual reality; Technology application; Physical objects; Virtual representations; Aerospace engineering; Digital twin application; digital twin applications; digital twin challenge; Digital twin challenge; digital twin technologies; Digital twin technology; Investments; State of the art; Technology challenges; Virtual environments; Virtual spaces; included
A8: 55QNNKSI | B8: journalArticle | C8: 2024 | D8: Barricelli, B.R.; Fogli, D. | E8: Digital Twins in Human-Computer Interaction: A Systematic Review | F8: International Journal of Human-Computer Interaction | H8: 10447318 (ISSN); 15327590 (ISSN) | I8: 10.1080/10447318.2022.2118189 | J8: https://www.scopus.com/inward/record.uri?eid=2-s2.0-85138270893&doi=10.1080%2F10447318.2022.2118189&partnerID=40&md5=f201ed7ffac05dac9bd2c18e89be14e9 | K8: With the spreading of Industry 4.0, cyber-physical systems, and tools for augmented and virtual reality, Digital Twin (DT) is gaining momentum in several areas of Computer Science and Engineering. This paper presents a systematic literature review that investigates the way DTs are described in Human-Computer Interaction (HCI) scientific literature. The study includes 23 papers selected through a systematic search on the 21 most ranked journals and conferences in the HCI area. As a result of this work, it appears clear that the way humans interact with DTs is a topic still far from being widely studied. A set of hints for future research about the relationship between HCI and DT constitute the main outcome of this paper. © 2024 Elsevier B.V., All rights reserved. | L8: 2024 | M8: 45977.672 | N8: 45981.507 | P8: 79-97 | R8: 2 | S8: 40 | U8: Int. J. Hum.-Comput. Interact. | AC8: English | AF8: Scopus | AJ8: Publisher: Taylor and Francis Ltd. | AN8: Systematic literature review; Cyber-physical systems; Systematic Review; Virtual reality; Human computer interaction; Cybe-physical systems; Embedded systems; Scientific literature; Augmented and virtual realities; Computer science and engineerings; Gaining momentum; Physical tool; Systematic searches; included
A9: 2VX6L29L | B9: conferencePaper | C9: 2026 | D9: Brarda, P.G.; Fernandez, G.; Ayala, N.F. | E9: Digital Twin, Digital Shadow or Digital Model? A Systematic Literature Review | F9: IFIP Advances in Information and Communication Technology | G9: 1868422X (ISSN); 18684238 (ISSN); 9783032007766 (ISBN); 9783031962301 (ISBN); 9783031949234 (ISBN); 9783031971143 (ISBN); 9783031962387 (ISBN); 9783031965210 (ISBN); 9780387291215 (ISBN); 9783319900223 (ISBN); 9783319162737 (ISBN); 1402080697 (ISBN) | I9: 10.1007/978-3-032-03538-7_22 | J9: https://www.scopus.com/inward/record.uri?eid=2-s2.0-105015479266&doi=10.1007%2F978-3-032-03538-7_22&partnerID=40&md5=f4812bfa7bde5366bad1c4f8aa0ac42b | K9: This study explores the evolution of the Digital Factory in the context of Industry 4.0, focusing on progression through the Digital Model, Digital Shadow and Digital Twin stages. It addresses a gap in the literature by differentiating these concepts, identifying their objectives and the technologies associated with each level. For this, a systematic review of the literature was carried out, using keyword combinations to identify relevant articles in the Scopus, Web of Science and Science Direct databases. In total, 47 articles were analyzed, allowing the development of a comprehensive understanding of the Digital Factory's technological internships and enablers. The study presents a conceptual framework that illustrates the transition from the Digital Model to the Digital Shadow and the Digital Twin, highlighting its transformative impact on manufacturing processes, with capabilities such as dynamic simulations, real-time monitoring, and predictive analytics. Technologies such as sensors, IoT, simulation, and artificial intelligence are analyzed at different levels of maturity. The results offer actionable insights for decision-makers, shedding light on the capabilities, hierarchies, and taxonomies of Digital Factory stages. In addition, a modular approach is proposed, which allows flexibility to meet the specific needs of projects, while ensuring scalability. The findings also serve as a resource for the development of roadmaps and budgets, facilitating successful implementations of the Digital Factory. This study contributes in an innovative way by systematically differentiating the concepts of Digital Model, Digital Shadow and Digital Twin, advancing both the theoretical understanding and the practical application of the Digital Factory in Industry 4.0. © 2025 Elsevier B.V., All rights reserved. | L9: 2026 | M9: 45977.672 | N9: 45981.503 | P9: 306-319 | S9: 766 IFIPAICT | AA9: Springer Science and Business Media Deutschland GmbH | AC9: English | AF9: Scopus | AJ9: Journal Abbreviation: IFIP Advances in Information and Communication Technology | AN9: Artificial intelligence; Internet of things; Industry 4.0; Systematic literature review; Digital Twin; Digital twin; Digital Factory; Budget control; Conceptual frameworks; Decision making; Digital factories; Digital Model; Digital modeling; Digital shadow; Digital Shadow; Dynamics simulation; Information systems; Information use; Manufacturing process; Real time monitoring; Systematic Review; Web of Science; included | AP9: Mizuyama, H.; Morinaga, E.; Nonaka, T.; Kaihara, T.; von Cieminski, G.; Romero, D. | BT9: IFIP Advances in Information and Communication Technology
A10: Z23UWXMR | B10: conferencePaper | C10: 2023 | D10: Carrión, E.; Pastor, Ó. | E10: A systematic review of methodologies for developing Digital Twins: Insights and recommendations for effective implementation | F10: CEUR Workshop Proc. | G10: 16130073 (ISSN); 9789666544899 (ISBN); 9788073780029 (ISBN); 9788024810256 (ISBN); 9789986342748 (ISBN); 9788073781712 (ISBN); 9782954494807 (ISBN); 9788024823911 (ISBN); 9789562361989 (ISBN); 8024810255 (ISBN); 807378002X (ISBN) | J10: https://www.scopus.com/inward/record.uri?eid=2-s2.0-85186955788&partnerID=40&md5=69a0173d87c1a6defc9d849b238e4cad | K10: Considering the diversity and complexity of the Digital Twins design and development approaches, understanding their methodological background is a significant problem. To face it, in this paper we present and discuss a systematic review that examines the methodologies currently employed in the development of Digital Twins. The study analyses relevant literature focusing on modelling and proposed methodologies for developing Digital Twins. The review identifies different approaches to Digital Twin development as the definition of structured frameworks and the proposal of step-by-step methodologies for building them. The review is intended to provide valuable insights for researchers, practitioners, and decision-makers on existing methodologies for developing effective and sound Digital Twin solutions. © 2024 Elsevier B.V., All rights reserved. | L10: 2023 | M10: 45977.672 | N10: 45981.502 | S10: 3645 | AA10: CEUR-WS | AC10: English | AF10: Scopus | AJ10: Journal Abbreviation: CEUR Workshop Proc. | AN10: Systematic literature review; Digital Twins; Methodology; Systematic Literature Review; Systematic Review; Decision makers; Design and Development; Design approaches; Development approach; Twin design; included | AP10: Sales, T.P.; Aveiro, D.; Mandelburger, M.M.; Proper, H.; Koschmider, A.; Asprion, P.M.; Marcelletti, A.; Morichetta, A.; Schneider, B.; Zech, P.; Kulkarni, V.; Breu, R.; Barat, S.; Poels, G.; Van Riel, J.; Calhau, R.F.; Bork, D.; Mulder, M.; de Kinderen, S.; Guerreiro, S.; Griffo, C.; Mandelburger, M.M.; Guerreiro, S. | BT10: CEUR Workshop Proceedings
A11: NFVJIDPL | B11: journalArticle | C11: 2021 | D11: Carvalho, R.; Rodrigues da Silva, A.R. | E11: Sustainability requirements of digital twin-based systems: A meta systematic literature review | F11: Applied Sciences (Switzerland) | H11: 20763417 (ISSN) | I11: 10.3390/app11125519 | J11: https://www.scopus.com/inward/record.uri?eid=2-s2.0-85108827458&doi=10.3390%2Fapp11125519&partnerID=40&md5=63dfdb02313f91047730df956c13b858 | K11: Sustainable development was defined by the UN in 1987 as development that meets the needs of the present without compromising the ability of future generations to meet their own needs, and this is a core concept in this paper. This work acknowledges the three dimensions of sustainability, i.e., economic, social, and environmental, but its focus is on this last one. A digital twin (DT) is frequently described as a physical entity with a virtual counterpart, and the data, connections between the two, implying the existence of connectors and blocks for efficient and effective data communication. This paper provides a meta systematic literature review (SLR) (i.e., an SLR of SLRs) regarding the sustainability requirements of DT-based systems. Numerous papers on the subject of DT were also selected because they cited the analyzed SLRs and were considered relevant to the purposes of this research. From the selection and analysis of 29 papers, several limitations and challenges were identified: the perceived benefits of DTs are not clearly understood; DTs across the product life cycle or the DT life cycle are not sufficiently studied; it is not clear how DTs can contribute to reducing costs or supporting decision-making; technical implementation of DTs must be improved and better integrated in the context of the IoT; the level of fidelity of DTs is not entirely evaluated in terms of their parameters, accuracy, and level of abstraction; and the ownership of data stored within DTs should be better understood. Furthermore, from our research, it was not possible to find a paper discussing DTs only in regard to environmental sustainability. © 2021 Elsevier B.V., All rights reserved. | L11: 2021 | M11: 45977.673 | N11: 45981.502 | R11: 12 | S11: 11 | U11: Appl. Sci. | AC11: English | AF11: Scopus | AJ11: Publisher: MDPI AG | AN11: Sustainable development; Internet of Things (IoT); Digital twins (DTs); Product design; Sustainability requirements; included
A12: 3H5AIY6V | B12: journalArticle | C12: 2025 | D12: Chen, S.; Turanoglu Bekar, E.; Bokrantz, J.; Skoogh, A. | E12: AI-enhanced digital twins in maintenance: Systematic review, industrial challenges, and bridging research–practice gaps | F12: Journal of Manufacturing Systems | H12: 02786125 (ISSN) | I12: 10.1016/j.jmsy.2025.07.006 | J12: https://www.scopus.com/inward/record.uri?eid=2-s2.0-105011843823&doi=10.1016%2Fj.jmsy.2025.07.006&partnerID=40&md5=59e79e71eab83ffa0cf8fec10c766bc6 | K12: The convergence of artificial intelligence (AI) and digital twin technology is reshaping maintenance strategies in the era of Industry 4.0. However, gaps persist between academic advancements and industrial adoption and expectation. This study systematically investigates the landscape of AI-enhanced digital twins for maintenance by integrating a systematic literature review (SLR) of related studies with in-depth interviews from industry practitioners. Our analysis reveals that while academia demonstrates robust applications of supervised, deep, and reinforcement learning to optimize digital twin models and prescribe data-driven actions, industrial implementation remains limited by challenges such as high scale dimension, data integration complexities, and insufficient workforce readiness. We identified and articulated three critical gap dimensions, scale, data, and model between academic research and industrial implementation and expectation. To bridge these gaps, we proposed a comprehensive five-layer framework for AI-enhanced digital twins, encompassing physical assets, data transmission, digital twins, AI analytics, and maintenance services. Actionable recommendations are provided, including the adoption of modular architectures, standardized data protocols, hybrid edge-cloud solutions, and targeted workforce upskilling. Our findings not only clarify the current state and challenges of AI-driven digital twins in maintenance but also offer a practical roadmap for accelerating their industrial implementation. This work advances the field by integrating insights from both academic research and industrial practice, offering concrete recommendations to support the practical realization of smart and sustainable maintenance practices. © 2025 Elsevier B.V., All rights reserved. | L12: 2025 | M12: 45977.672 | N12: 45981.501 | P12: 678-699 | S12: 82 | U12: J Manuf Syst | AC12: English | AF12: Scopus | AJ12: Publisher: Elsevier B.V. | AN12: Artificial intelligence; Engineering education; Systematic literature review; Digital twins; Data integration; Digital twin; Predictive maintenance; Gap analysis; Prescriptive maintenance; Predictive analytics; Engineering research; Industrial research; Systematic Review; Academic research; Industrial adoption; Industrial challenges; Industrial implementation; Maintenance strategies; Personnel; included
A13: E63P3N3D | B13: journalArticle | C13: 2023 | D13: Correia, J.B.; Abel, M.; Becker, K. | E13: Data management in digital twins: a systematic literature review | F13: Knowledge and Information Systems | H13: 02193116 (ISSN); 02191377 (ISSN) | I13: 10.1007/s10115-023-01870-1 | J13: https://www.scopus.com/inward/record.uri?eid=2-s2.0-85153108953&doi=10.1007%2Fs10115-023-01870-1&partnerID=40&md5=33e53121b1ddf8796cf152499abf999c | K13: The Internet of Things (IoT) and continuous advances in data-gathering devices and techniques have significantly increased the amount of relevant data that can be leveraged for innovative real-time, data-driven applications. Digital Twins (DTs) are virtual representations of physical objects, which are fully integrated and in which the automatic data exchange occurs in a bidirectional way. Modern DTs follow a five-component architecture, which includes an explicit Data Management (DM) component that acts as a bridge between the other systems. However, there is no clarity on its role and functionalities. This article presents a Systematic Literature Review on DM solutions proposed in the DT context. We analyzed DM under the Big Data chain of activities to add value to data, highlighting key issues to be addressed: data heterogeneity, interoperability, integration, data search, and quality. In addition to surveying existing solutions for handling these issues, we contextualized them in the domain and function for which the DT was proposed, the type of data dealt with, and the technological infrastructure. Our main findings revealed that the maturity level assumed for the DM component is at an early stage. The most mature solutions were proposed for the industry domain, and many of them assume humans as the ultimate information consumers. Data integration is the prevalent DM issue addressed due to the bridging role of the DM component, and cloud computing is the key implementation technology. Among the research opportunities are reference data management architectures, adoption of industry standards and ontologies, interoperability among distinct DTs, the development of agnostic standard implementations, and data provenance mechanisms. © 2023 Elsevier B.V., All rights reserved. | L13: 2023 | M13: 45977.672 | N13: 45981.499 | P13: 3165-3196 | R13: 8 | S13: 65 | U13: Knowl. Inf. Systems. Syst. | AC13: English | AF13: Scopus | AJ13: Publisher: Springer Science and Business Media Deutschland GmbH | AN13: Internet of things; Systematic literature review; Information management; Data integration; Digital twin; Interoperability; Electronic data interchange; Real-time data; Physical objects; Virtual representations; Search engines; Big data; Component architectures; Data gathering; Data management; Data management solution; Data-driven applications; Fully integrated; Management components; included
A14: GVXE7DQ6 | B14: journalArticle | C14: 2022 | D14: da Cruz, R.J.M.; Tonin, L.A. | E14: Systematic review of the literature on Digital Twin: a discussion of contributions and a framework proposal | F14: Gestao e Producao | H14: 0104530X (ISSN) | I14: 10.1590/1806-9649-2022V29E9621 | J14: https://www.scopus.com/inward/record.uri?eid=2-s2.0-85135149735&doi=10.1590%2F1806-9649-2022V29E9621&partnerID=40&md5=6e38367059feb9e75f249d57b6be36e4 | K14: This study aimed to investigate the definitions, requirements and applications of Digital Twin (DT) models, and for that, a systematic literature review was carried out using Science Direct, Scopus and Web of Science as the bases for the articles. The method used was based on bibliometric analysis of the 332 articles extracted from the bases and a content analysis, which sought to identify contributions, common topics and gaps among the 17 articles that were filtered and identified as relevant to the second objective of this work, the framework proposal. The analyzed sample indicated that authors diverge on the definitions and use different processes to build a DT, models that seek to represent elements of the real environment, which could be products and/or processes/services, with the objective of being a tool for performance monitoring, simulation of scenarios and source of information for decision making. The use of software that often does not have trial licenses or versions for students was also observed in the sample, based on this point and on the analyzed content, an attempt was made to build a conceptual framework for the construction of a DT model in a game engine, using software that does not require licenses. © 2022 Elsevier B.V., All rights reserved. | L14: 2022 | M14: 45977.672 | N14: 45981.499 | S14: 29 | U14: Gestao Prod. | V14: Revisão sistemática da literatura sobre Digital Twin: discussão sobre contribuições e proposta de um framework | AC14: English | AF14: Scopus | AJ14: Publisher: Brazilian Institute for Information in Science and Technology | AN14: Digital Twin; Framework; Game Engines; included
A15: VHWX9WSH | B15: journalArticle | C15: 2022 | D15: Dos Santos, C.H.; Montevechi, J.A.B.; de Queiroz, J.A.; Miranda, R.; Leal, F. | E15: Decision support in productive processes through DES and ABS in the Digital Twin era: a systematic literature review | F15: International Journal of Production Research | H15: 1366588X (ISSN); 00207543 (ISSN) | I15: 10.1080/00207543.2021.1898691 | J15: https://www.scopus.com/inward/record.uri?eid=2-s2.0-85102693068&doi=10.1080%2F00207543.2021.1898691&partnerID=40&md5=a4c004c82536f6bb4277f27b7db2576b | K15: The use of simulation to support decision-making in productive processes (goods and services) is already an established research field. However, with the availability of solutions and technologies, simulation is no longer a tool with limited scope and analysis. In this case, the integration of simulation with physical systems is considered to allow virtual models to be sensitive to physical changes and aligned with the current state of processes, forming the so-called Digital Twin. Therefore, the main purpose of this article is to present a systematic literature review of the use of simulation as Digital Twin to support decision-making. We considered studies published in scientific journals and conference proceedings that include the use of Discrete Event Simulation (DES) and/or Agent-Based Simulation (ABS). Although the Digital Twin concept has appeared in recent years, we noted that its principle has been used for decades when it comes to decision-making through simulation. Moreover, there are still many discussions and uncertainties regarding the simulation model in this research field, such as the degree of autonomy, synchronisation, and connection. These and other key issues are discussed and some research opportunities are highlighted, such as the need for constant model validation and integration between various models. © 2022 Elsevier B.V., All rights reserved. | L15: 2022 | M15: 45977.673 | N15: 45981.49 | P15: 2662-2681 | R15: 8 | S15: 60 | U15: Int J Prod Res | AC15: English | AF15: Scopus | AJ15: Publisher: Taylor and Francis Ltd. | AN15: Systematic literature review; Digital Twin; systematic literature review; Digital twin; Decision making; Physical systems; Decision support systems; Discrete event simulation; decision-making; Agent based simulation; agent-based simulation; Decision supports; Degree of autonomy; discrete event simulation; Productive process; Research opportunities; Scientific journals; included
A16: AWNIYLEJ | B16: conferencePaper | C16: 2023 | D16: Fett, M.; Wilking, F.; Goetz, S.; Kirchner, E.; Wartzack, S. | E16: Sensor selection and integration for Cyber-Physical Systems in context of Digital Twins - A systematic review of requirements | F16: Annu. Syst. Syst. Eng. Conf., SoSe | G16: 9798350327236 (ISBN) | I16: 10.1109/SoSE59841.2023.10178669 | J16: https://www.scopus.com/inward/record.uri?eid=2-s2.0-85166732531&doi=10.1109%2FSoSE59841.2023.10178669&partnerID=40&md5=3c1fa869111fb74c669f44a07a57df6a | K16: Digital Twins process real-time data collected from a Physical Twin. This real-time data is often measurement by sensors, which must be selected and integrated during the development or modification of the physical twin. In this paper, a systematic literature review on sensors for Digital Twins and Cyber-Physical Systems is conducted. The results are mapped into a framework for selection and integration. From this, the special requirements for the sensors that arise from the use of Digital Twins can be identified. © 2023 Elsevier B.V., All rights reserved. | L16: 2023 | M16: 45977.672 | N16: 45981.484 | AA16: Institute of Electrical and Electronics Engineers Inc. | AC16: English | AF16: Scopus | AJ16: Journal Abbreviation: Annu. Syst. Syst. Eng. Conf., SoSe | AN16: Systematic literature review; Digital Twin; Cyber-physical systems; Systematic Review; Integration; Cybe-physical systems; Embedded systems; Real-time data; Cyber Physical System; Cyber-Physical System; Literature reviews; In contexts; Literature Review; Method; Sensor integration; Sensor selection; included
A17: 6SMBTIWS | B17: conferencePaper | C17: 2025 | D17: Filho, P.T.J.C.; Junior, O.C. | E17: Digital Twin in Industry 4.0: Systematic review and content analysis and an architectural reference model | F17: Procedia Comput. Sci. | G17: 18770509 (ISSN); 9781510849914 (ISBN) | I17: 10.1016/j.procs.2025.02.016 | J17: https://www.scopus.com/inward/record.uri?eid=2-s2.0-105000464865&doi=10.1016%2Fj.procs.2025.02.016&partnerID=40&md5=8443907cbbc36afa07529bf89cc4771a | K17: Recent findings showed that Digital Twin served multiple constituencies. However, the dilemma between scope and scale requires a sophisticated reference architecture, an appropriate set of technologies and an appropriate business model. Most studies in Digital Twin have focused only on manufacturing and proposed explicit structures and architecture, which have faced challenges in supporting different levels of integration through an agile process. Furthermore, no known empirical research has focused on exploring the relationships between the Digital Twin and mass individualization. Therefore, the main objective of this study was to identify suitable Industry 4.0 technologies and a holistic reference architecture model to realize the most challenging Digital Twin-enabled applications. In this study, a Digital Twin reference architecture was developed and applied in an industrial case. Furthermore, the Digital Twin as a Service (DTaaS) paradigm used for the digital transformation of unique wetlands with considerable advantages including smart scheduled maintenance, real-time monitoring, remote control and forecasting functionalities. The findings indicate that there is a significant relationship between the capabilities of Digital Twin as a Service and mass individualization. © 2025 Elsevier B.V., All rights reserved. | L17: 2025 | M17: 45977.672 | N17: 45981.484 | P17: 2919-2928 | S17: 253 | AA17: Elsevier B.V. | AC17: English | AF17: Scopus | AJ17: Journal Abbreviation: Procedia Comput. Sci. | AN17: Content analysis; Digital transformation; Digital Twin; digital transformation; industry 4.0; Reference architecture; Systematic Review; Smart manufacturing; Agile process; Business models; Empirical research; Individualisation; Level of integrations; Reference modeling; included | AP17: Solina, V.; Longo, F.; Romero, D. | BT17: Procedia Computer Science
A18: X2RYXN8W | B18: journalArticle | C18: 2025 | D18: Gaffinet, B.; Al Haj Ali, J.; Naudet, Y.; Panetto, H. | E18: Human Digital Twins: A systematic literature review and concept disambiguation for industry 5.0 | F18: Computers in Industry | H18: 01663615 (ISSN) | I18: 10.1016/j.compind.2024.104230 | J18: https://www.scopus.com/inward/record.uri?eid=2-s2.0-85213848996&doi=10.1016%2Fj.compind.2024.104230&partnerID=40&md5=91e614ad93f82aa9749e6d781c80f36b | K18: Human Digital Twins (HDTs) are an emerging concept with the potential to create human-centric systems for Industry 5.0. The concept has rapidly spread to new application domains, most notably Healthcare, leading to diverging conceptual interpretations. This Systematic Literature Review analyses the conceptual understanding of HDTs across all application domains to clarify the conceptual foundation. Our review reveals a consensus that an HDT's twinned entity is a human individual. However, there is little agreement on the data flows between the individual and their HDT. We address this shortcoming by proposing three categories based on the level of data integration: Human Digital Models, Human Digital Shadows, and Human Digital Twins. Finally, we synthesise our findings in a domain-agnostic general definition for HDT. We highlight an edge case where the twinned entity is a human individual alongside a strongly coupled technical system, and name it augmented Human Digital Twin (aHDT). The definition and categorisation scheme provide the needed conceptual clarity for inter-disciplinary collaboration to address open challenges. Notable challenges are sensing human data, reliable data transfers and modelling, especially behavioural modelling. Additional ethical issues concerning security, privacy and consent are central to successful HDT adoption. We call for cross-disciplinary efforts to establish a standardised framework and ethical guidelines to enable future developments. © 2025 Elsevier B.V., All rights reserved. | L18: 2025 | M18: 45977.672 | N18: 45981.483 | S18: 166 | U18: Comput Ind | AC18: English | AF18: Scopus | AJ18: Publisher: Elsevier B.V. | AN18: Systematic literature review; Digital Twin; Industry 5.0; Human Digital Twin; Human-centricity; Applications domains; Conceptual foundations; Conceptual understanding; Dataflow; Human centricities; Human digital twin; Human-centric; New applications; included
A19: YNFWX7UL | B19: journalArticle | C19: 2025 | D19: Ghanbarifard, R.; Almeida, A.H.; Azevedo, A. | E19: Structuring Complex System for Digital Twin Development: A Systematic Scoping Review | F19: IEEE Access | H19: 21693536 (ISSN) | I19: 10.1109/ACCESS.2025.3610067 | J19: https://www.scopus.com/inward/record.uri?eid=2-s2.0-105016645625&doi=10.1109%2FACCESS.2025.3610067&partnerID=40&md5=e9cffb45328dae5702b27a2fb633e97d | K19: Complex systems, characterised by high interconnectedness and unpredictability, demand structured approaches to support decision-making, system integration, and operational efficiency. This study aims to develop a comprehensive understanding of these systems to facilitate the implementation of Digital Twins (DTs) in Complex Operations Environments (COEs). A Systematic Literature Review (SLR), following PRISMA methodology, is conducted and complemented by a grounded theory approach to identify, organise, and synthesise system characteristics. The result is a hierarchical conceptualisation comprising eight core categories that capture the essential dimensions of complexity, including: Process and System Interoperability, Human Relationships, Behaviour/Nature, Products and Services, Multi-processes, Performance, System Structure, and Management and Skill Requirements. This framework offers a structured foundation for designing and implementing DT-based decision support in COEs. © 2025 Elsevier B.V., All rights reserved. | L19: 2025 | M19: 45977.672 | N19: 45981.477 | P19: 162285-162303 | S19: 13 | U19: IEEE Access | AC19: English | AF19: Scopus | AJ19: Publisher: Institute of Electrical and Electronics Engineers Inc. | AN19: Digital twin; Decision making; Large scale systems; Behavioral research; digital twins; Decision support systems; Complex operations; Complex system characteristic; Complex systems characteristics; complexity conceptualization; Complexity conceptualization; Decision-making systems; hierarchical conceptualization; Hierarchical conceptualization; Hierarchical systems; operational environments; Operational environments; Scoping review; Structured approach; System characteristics; system engineering; System integration; included
A20: ESDRTMG9 | B20: journalArticle | C20: 2024 | D20: Guinea-Cabrera, M.A.; Holgado-Terriza, J.A. | E20: Digital Twins in Software Engineering—A Systematic Literature Review and Vision | F20: Applied Sciences (Switzerland) | H20: 20763417 (ISSN) | I20: 10.3390/app14030977 | J20: https://www.scopus.com/inward/record.uri?eid=2-s2.0-85196390166&doi=10.3390%2Fapp14030977&partnerID=40&md5=5eb84543f477f4596d8e60886c4e2f47 | K20: Featured Application: Secure Integration of the IoT and Digital Twins. Digital twins are a powerful consequence of digital transformation. In fact, they have been applied to many industries to enhance operations, predict needs, improve decision making, or optimize performance, even though the definition of digital twins is still evolving. However, their impact on the software industry is still limited. Thus, this work aims to analyze the current adoption of digital twins in the software industry as a potential path to integrate them into application lifecycle management. To achieve this objective, first, the significant characteristics of current digital twins are analyzed in their application to manufacturing to understand how the knowledge and the lessons learned can be transferred to the software industry. Second, a systematic literature review was conducted on Scopus, the Web of Science, and the ScienceDirect database. The literature review revealed 93 documents after data screening and cleaning 251 initial documents. Our main findings are that digital twins are already influencing and will significantly affect the software industry, revolutionizing various aspects of the software development lifecycle. This study tackles what identifies a digital twin in the software industry, the specific domains and areas where they can be applied in the software lifecycle, and the proposed approaches explored to build digital twins for developing, deploying, and maintaining software systems. Finally, this study proposes some guidelines for building digital twins in the context of application lifecycle management. Determining an appropriate roadmap shortly is essential to achieve a widespread applicability to building suitable digital twins and preparing organizations for the software industry. © 2024 Elsevier B.V., All rights reserved. | L20: 2024 | M20: 45977.672 | N20: 45981.476 | R20: 3 | S20: 14 | U20: Appl. Sci. | AC20: English | AF20: Scopus | AJ20: Publisher: Multidisciplinary Digital Publishing Institute (MDPI) | AN20: digital twin; digital transformation; software development; software engineering; software industry; included
A21: WXIMSBB7 | B21: journalArticle | C21: 2025 | D21: Hunde, J.M.; Ochono, T.S.; Senevirathne, D.; Eneyew, D.D.; Bitsuamlak, G.T.; Capretz, M.A.M.; Grolinger, K. | E21: Data-driven and physics-based modeling approaches and their integration in building digital twins: A systematic review | F21: Journal of Building Engineering | H21: 23527102 (ISSN) | I21: 10.1016/j.jobe.2025.114214 | J21: https://www.scopus.com/inward/record.uri?eid=2-s2.0-105017734857&doi=10.1016%2Fj.jobe.2025.114214&partnerID=40&md5=c1f58863737ce1119fe9d5a1aa854ffb | K21: Interest in digital twin technology has grown significantly within the building sector as part of the broader digital transformation in the architecture, engineering, and construction industry. A building digital twin is a virtual replica that captures a building's static and dynamic behavior through data, information, and models. Digital twin models can be developed using data-driven or physics-based approaches, each with distinct advantages and limitations. Data-driven models can learn complex behaviors from data and scale well, but they require large datasets and often lack interpretability. In contrast, physics-based models offer interpretability and generalizability through fundamental principles but can be computationally demanding. Consequently, building digital twins can benefit greatly from integrating both approaches through hybrid modeling. However, the literature lacks a comprehensive analysis of integration strategies within building digital twins. This study addresses that gap by reviewing advances in data-driven and physics-based modeling and analyzing various integration levels. The results show that most studies rely on siloed models, using either approach independently without leveraging their complementary strengths. Some adopted sequential integration, where one model informs the other but lacks real-time or iterative feedback. A few achieved coupled integration, involving active data exchange and collaboration between models. Only three studies explored fusion integration, where both approaches are fully unified into a single model. Based on this review, a method is proposed for selecting the appropriate level of integration, considering factors such as data availability, interpretability, generalizability, and domain knowledge. Finally, key research gaps and future directions are identified to guide further work. © 2025 Elsevier B.V., All rights reserved. | L21: 2025 | M21: 45977.672 | N21: 45981.471 | S21: 114 | U21: J. Build. Eng. | AC21: English | AF21: Scopus | AJ21: Publisher: Elsevier Ltd | AN21: Buildings; Data integration; Digital twin; Construction industry; Building digital twin; Data-driven modeling; Hybrid modeling; Model integration; Physics-based modeling; Systematic Review; Data driven; Building Information Model; Data-driven model; Electronic data interchange; Hybrid model; In-buildings; Integration; Interpretability; Iterative methods; Large datasets; Metadata; Modeling approach; Models integration; Physics-based models; Virtual reality; included
A22: YWMG9KT2 | B22: journalArticle | C22: 2020 | D22: Jones, D.; Snider, C.; Nassehi, A.; Yon, J.; Hicks, B. | E22: Characterising the Digital Twin: A systematic literature review | F22: CIRP Journal of Manufacturing Science and Technology | H22: 17555817 (ISSN) | I22: 10.1016/j.cirpj.2020.02.002 | J22: https://www.scopus.com/inward/record.uri?eid=2-s2.0-85081219520&doi=10.1016%2Fj.cirpj.2020.02.002&partnerID=40&md5=48ff58a3a8fe6d1030612672627a9ff4 | K22: While there has been a recent growth of interest in the Digital Twin, a variety of definitions employed across industry and academia remain. There is a need to consolidate research such to maintain a common understanding of the topic and ensure future research efforts are to be based on solid foundations. Through a systematic literature review and a thematic analysis of 92 Digital Twin publications from the last ten years, this paper provides a characterisation of the Digital Twin, identification of gaps in knowledge, and required areas of future research. In characterising the Digital Twin, the state of the concept, key terminology, and associated processes are identified, discussed, and consolidated to produce 13 characteristics (Physical Entity/Twin; Virtual Entity/Twin; Physical Environment; Virtual Environment; State; Realisation; Metrology; Twinning; Twinning Rate; Physical-to-Virtual Connection/Twinning; Virtual-to-Physical Connection/Twinning; Physical Processes; and Virtual Processes) and a complete framework of the Digital Twin and its process of operation. Following this characterisation, seven knowledge gaps and topics for future research focus are identified: Perceived Benefits; Digital Twin across the Product Life-Cycle; Use-Cases; Technical Implementations; Levels of Fidelity; Data Ownership; and Integration between Virtual Entities; each of which are required to realise the Digital Twin. © 2020 Elsevier B.V., All rights reserved. | L22: 2020 | M22: 45977.673 | N22: 45981.468 | P22: 36-52 | S22: 29 | U22: CIRP J. Manuf. Sci. Technol. | AC22: English | AF22: Scopus | AJ22: Publisher: Elsevier Ltd | AN22: Systematic literature review; Digital Twin; Digital twin; Virtual Twin; Life cycle; Virtual reality; Physical connections; Product life cycles; Perceived benefits; Physical environments; Technical implementation; Virtual connections; included
A23: BN2653D2 | B23: journalArticle | C23: 2024 | D23: Karabulut, E.; Pileggi, S.F.; Groth, P.; Degeler, V. | E23: Ontologies in digital twins: A systematic literature review | F23: Future Generation Computer Systems | H23: 0167739X (ISSN) | I23: 10.1016/j.future.2023.12.013 | J23: https://www.scopus.com/inward/record.uri?eid=2-s2.0-85181034395&doi=10.1016%2Fj.future.2023.12.013&partnerID=40&md5=b0373df306d2e0b07ca6325f30170f8c | K23: Digital Twins (DT) facilitate monitoring and reasoning processes in cyber–physical systems. They have progressively gained popularity over the past years because of intense research activity and industrial advancements. Cognitive Twins is a novel concept, recently coined to refer to the involvement of Semantic Web technology in DTs. Recent studies address the relevance of ontologies and knowledge graphs in the context of DTs, in terms of knowledge representation, interoperability and automatic reasoning. However, there is no comprehensive analysis of how semantic technologies, and specifically ontologies, are utilized within DTs. This Systematic Literature Review (SLR) is based on the analysis of 82 research articles, that either propose or benefit from ontologies with respect to DT. The paper uses different analysis perspectives, including a structural analysis based on a reference DT architecture, and an application-specific analysis to specifically address the different domains, such as Manufacturing and Infrastructure. The review also identifies open issues and possible research directions on the usage of ontologies and knowledge graphs in DTs. © 2024 Elsevier B.V., All rights reserved. | L23: 2024 | M23: 45977.672 | N23: 45981.465 | P23: 442-456 | S23: 153 | U23: Future Gener Comput Syst | AC23: English | AF23: Scopus | AJ23: Publisher: Elsevier B.V. | AN23: Internet of things; Systematic literature review; Digital twin; Cyber-physical systems; Cyber–physical systems; Knowledge graphs; Ontology; Semantic web; Industrial research; Cybe-physical systems; Ontology's; Knowledge graph; Monitoring process; Ontology graphs; Reasoning process; Research activities; Semantic Web; Semantic-Web; included
A24: 47TR8Z9D | B24: journalArticle | C24: 2024 | D24: Kreuzer, T.; Papapetrou, P.; Zdravkovic, J. | E24: Artificial intelligence in digital twins—A systematic literature review | F24: Data and Knowledge Engineering | H24: 0169023X (ISSN) | I24: 10.1016/j.datak.2024.102304 | J24: https://www.scopus.com/inward/record.uri?eid=2-s2.0-85190070128&doi=10.1016%2Fj.datak.2024.102304&partnerID=40&md5=3ba1ba433815b394e18632a808eb6a25 | K24: Artificial intelligence and digital twins have become more popular in recent years and have seen usage across different application domains for various scenarios. This study reviews the literature at the intersection of the two fields, where digital twins integrate an artificial intelligence component. We follow a systematic literature review approach, analyzing a total of 149 related studies. In the assessed literature, a variety of problems are approached with an artificial intelligence-integrated digital twin, demonstrating its applicability across different fields. Our findings indicate that there is a lack of in-depth modeling approaches regarding the digital twin, while many articles focus on the implementation and testing of the artificial intelligence component. The majority of publications do not demonstrate a virtual-to-physical connection between the digital twin and the real-world system. Further, only a small portion of studies base their digital twin on real-time data from a physical system, implementing a physical-to-virtual connection. © 2024 Elsevier B.V., All rights reserved. | L24: 2024 | M24: 45977.672 | N24: 45981.463 | S24: 151 | U24: Data Knowl Eng | AC24: English | AF24: Scopus | AJ24: Publisher: Elsevier B.V. | AN24: Artificial intelligence; Machine learning; Data mining; Literature review; Systematic literature review; Digital twin; Business intelligence; Modeling approach; E-learning; Machine-learning; Real-time data; Applications domains; Literature reviews; Business-intelligence; Depth models; Physical connections; Real-world system; included
A25: D3F2QJVE | B25: journalArticle | C25: 2024 | D25: Kuštelega, M.; Mekovec, R.; Shareef, A. | E25: Privacy and security challenges of the digital twin: systematic literature review | F25: Journal of Universal Computer Science | H25: 0948695X (ISSN); 09486968 (ISSN) | I25: 10.3897/jucs.114607 | J25: https://www.scopus.com/inward/record.uri?eid=2-s2.0-85215411229&doi=10.3897%2Fjucs.114607&partnerID=40&md5=922bff14ca4a6e45eee740c5d3346c01 | K25: As technology advances and becomes more extensively used, digital twins are likely to play an increasingly crucial role in defining the future of industry, trade, and society. Despite the stated advantages and potential of digital twin technology, certain research and implementation gaps exist, which have hindered the adoption and advancement of digital twins. This study investigates how current research on the digital twin implementations has been positioned in front of practical challenges focused on privacy and security issues. The research method adopted was a systematic literature review, employing the PRISMA approach. A total of 47 publications were identified and analyzed. The results indicate that the privacy and security challenges for digital twin implementation are complicated and may be divided into six primary groups: (1) data privacy, (2) data security, (3) data management, (4) data infrastructure and standardization, (5) ethical and moral issues, (6) legal and social issues. © 2025 Elsevier B.V., All rights reserved. | L25: 2024 | M25: 45977.672 | N25: 45981.461 | P25: 1782-1806 | R25: 13 | S25: 30 | U25: J. Univers. Comput. Sci. | AC25: English | AF25: Scopus | AJ25: Publisher: IICM | AN25: literature review; Digital twin; privacy; challenges; PRISMA; security; included
A26: 6ELYDV5G | B26: journalArticle | C26: 2024 | D26: Listl, F.G.; Dittler, D.; Hildebrandt, G.; Stegmaier, V.; Jazdi, N.; Weyrich, M. | E26: Knowledge Graphs in the Digital Twin: A Systematic Literature Review About the Combination of Semantic Technologies and Simulation in Industrial Automation | F26: IEEE Access | H26: 21693536 (ISSN) | I26: 10.1109/ACCESS.2024.3514923 | J26: https://www.scopus.com/inward/record.uri?eid=2-s2.0-85212072573&doi=10.1109%2FACCESS.2024.3514923&partnerID=40&md5=8370c37531ebbe7cb82c6cd7369a4d70 | K26: The ongoing digitization of the industrial sector has reached a pivotal juncture with the emergence of Digital Twins, offering a digital representation of physical assets and processes. One key aspect of these digital representations is the utilization of simulation models, enabling a deeper insight into the asset's current state and its characteristics. This paper asserts that the next evolutionary step in this digitization journey involves the integration of intelligent linkages between diverse simulation models within the Digital Twin framework. Crucially, for the Digital Twin to be a scalable and cost-effective solution, there is a pressing need for automated adaption, (re-)configuration, and generation of simulation models. Recognizing the inherent challenges in achieving such automation, this paper analyses the utilization of knowledge graphs as a potentially very suitable technological solution. Knowledge graphs, acting as interconnected and interrelated databases, provide a means of seamlessly integrating different data sources, facilitating the efficient integration and automated adaption of data and (simulation) models in the Digital Twin. We conducted a comprehensive literature review to analyze the current landscape of knowledge graphs in the context of Digital Twins with a focus on simulation models. By addressing the challenges associated with scalability and maintenance, this research contributes to the effective adoption of Digital Twins in the industrial sector, paving the way for enhanced efficiency, adaptability, and resilience in the face of evolving technological landscapes. © 2024 Elsevier B.V., All rights reserved. | L26: 2024 | M26: 45977.672 | N26: 45981.459 | P26: 187828-187843 | S26: 12 | U26: IEEE Access | AC26: English | AF26: Scopus | AJ26: Publisher: Institute of Electrical and Electronics Engineers Inc. | AN26: Simulation; simulation; Systematic literature review; Digital twin; Knowledge graphs; Industrial sector; 'current; Knowledge graph; Digital representations; Digitisation; Industrial automation; knowledge graph; semantic technologies; Semantic technologies; Simulation model; included
A27: 7HEYRKR8 | B27: journalArticle | C27: 2023 | D27: Liu, X.; Jiang, D.; Tao, B.; Xiang, F.; Jiang, G.; Sun, Y.; Kong, J.; Li, G. | E27: A systematic review of digital twin about physical entities, virtual models, twin data, and applications | F27: Advanced Engineering Informatics | H27: 14740346 (ISSN) | I27: 10.1016/j.aei.2023.101876 | J27: https://www.scopus.com/inward/record.uri?eid=2-s2.0-85147190635&doi=10.1016%2Fj.aei.2023.101876&partnerID=40&md5=1fef1c7d5560fff85bb43b7e52e3f651 | K27: The digital twin is a crucial technology for realizing smart manufacturing and industrial digital transformation, which has received extensive attention and research from industry and academia. After 20 years of development, the application area of digital twins has been pervasive. Due to the diversity of application areas, various reference models and research methods have been presented for the components of the digital twin. Therefore, this paper provides systematic research of current studies on the basic components of the digital twin. This paper analyzed 117 articles from 2017 to 2022. By clarifying the relationship between the digital twin and the cyber-physical system, it first clarified the definition, characteristics, and application areas of the digital twin. On this basis, the research methodology of the core components of the digital twin (physical entities, virtual models, and twin data) is analyzed. At the same time, the application areas of digital twins are analyzed and delineated, and the application potential of the digital twin is explored. Finally, the research results and future research recommendations are presented. © 2023 Elsevier B.V., All rights reserved. | L27: 2023 | M27: 45977.672 | N27: 45980.909 | S27: 55 | U27: Adv. Eng. Inf. | AC27: English | AF27: Scopus | AJ27: Publisher: Elsevier Ltd | AN27: Digital transformation; Digital Twin; Applications; Physical entity; Twin data; Virtual model; Industrial research; Systematic Review; Embedded systems; Smart manufacturing; Virtual models; Reference modeling; Application area; Crucial technology; Model method; included
A28: AQHYP64S | B28: journalArticle | C28: 2025 | D28: Massaro, A. | E28: Electronic Artificial Intelligence and Digital Twins in Industry 5.0: A Systematic Review and Perspectives | F28: Machines | H28: 20751702 (ISSN) | I28: 10.3390/machines13090755 | J28: https://www.scopus.com/inward/record.uri?eid=2-s2.0-105017090734&doi=10.3390%2Fmachines13090755&partnerID=40&md5=cca26277ff5f00407bca2077f6ce4268 | K28: This review analyzes the Electronic Digital Twin (EDT) tools characterizing the industrial transformation phase from Industry 4.0 to Industry 5.0. The goal is to provide innovative research EDT solutions to integrate in manufacturing production processes. Specifically, this research is focused on the possibility of combining the advanced technologies and electronics and mechatronics of industrial machines with Artificial Intelligence (AI) algorithms. Furthermore, this review provides important elements about possible future implementations of AI-EDTs and some circuital examples to support the understanding of the concept of circuit simulation in EDT models. EDTs are useful to comprehend the modeling concepts functional to the AI application using the output of the circuit simulations. The output of the circuit is used to train the AI model, thus strengthening the capability to classify and predict the real behavior of production machines with a good accuracy. This review discusses perspectives, limits, and advantages of EDTs and is useful to define new research patterns integrating structured EDTs in advanced industrial environments. The focus of this paper is the definition of possible perspectives of EDT implementations, including AI, in data-driven processes in specific strategic areas of industrial research by classifying the scientific topics in six main pillars. This paper is also suitable for the researcher to develop innovative topics for projects scaled into different work packages based on EDT facilities. © 2025 Elsevier B.V., All rights reserved. | L28: 2025 | M28: 45977.672 | N28: 45980.906 | R28: 9 | S28: 13 | U28: Mach. | AC28: English | AF28: Scopus | AJ28: Publisher: Multidisciplinary Digital Publishing Institute (MDPI) | AN28: Industry 5.0; advanced manufacturing modeling; AI-based modeling; Electronic Digital Twins; included
A29: K445EJH6 | B29: journalArticle | C29: 2025 | D29: Mayer, A.; Greif, L.; Häußermann, T.M.; Otto, S.; Kastner, K.; El Bobbou, S.; Chardonnet, J.-R.; Reichwald, J.; Fleischer, J.; Ovtcharova, J. | E29: Digital Twins, Extended Reality, and Artificial Intelligence in Manufacturing Reconfiguration: A Systematic Literature Review | F29: Sustainability (Switzerland) | H29: 20711050 (ISSN) | I29: 10.3390/su17052318 | J29: https://www.scopus.com/inward/record.uri?eid=2-s2.0-86000775946&doi=10.3390%2Fsu17052318&partnerID=40&md5=43be33f4644d39296f2d527a1272e2af | K29: This review draws on a systematic literature review and bibliometric analysis to examine how Digital Twins (DTs), Extended Reality (XR), and Artificial Intelligence (AI) support the reconfiguration of Cyber–Physical Systems (CPSs) in modern manufacturing. The review aims to provide an updated overview of these technologies’ roles in CPS reconfiguration, summarize best practices, and suggest future research directions. In a two-phase process, we first analyzed related work to assess the current state of assisted manufacturing reconfiguration and identify gaps in existing reviews. Based on these insights, an adapted PRISMA methodology was applied to screen 165 articles from the Scopus and Web of Science databases, focusing on those published between 2019 and 2025 addressing DT, XR, and AI integration in Reconfigurable Manufacturing Systems (RMSs). After applying the exclusion criteria, 38 articles were selected for final analysis. The findings highlight the individual and combined impact of DTs, XR, and AI on reconfiguration processes. DTs notably reduce reconfiguration time and improve system availability, AI enhances decision-making, and XR improves human–machine interactions. Despite these advancements, a research gap exists regarding the combined application of these technologies, indicating potential areas for future exploration. The reviewed studies recognized limitations, especially due to diverse study designs and methodologies that may introduce risks of bias, yet the review offers insight into the current DT, XR, and AI landscape in RMS and suggests areas for future research. © 2025 Elsevier B.V., All rights reserved. | L29: 2025 | M29: 45977.672 | N29: 45980.905 | R29: 5 | S29: 17 | U29: Sustainability | AC29: English | AF29: Scopus | AJ29: Publisher: Multidisciplinary Digital Publishing Institute (MDPI) | AN29: artificial intelligence; machine learning; literature review; decision making; digital twins; cyber–physical systems; extended reality; human–machine interaction; manufacturing; nature-society relations; reconfigurable manufacturing systems; included
A30: JBAVLRA5 | B30: bookSection | C30: 2022 | D30: Ofosu, R.; Hosseinian-Far, A.; Sarwar, D. | E30: Digital Twin Technologies, Architecture, and Applications: A Comprehensive Systematic Review and Bibliometric Analysis | F30: Adv. Sci. Tech. Sec. Appl. | G30: 23639466 (ISSN); 16135113 (ISSN) | J30: https://www.scopus.com/inward/record.uri?eid=2-s2.0-85129655945&doi=10.1007%2F978-3-030-98225-6_5&partnerID=40&md5=de0feb522c7689344c18f217a7c97903 | K30: Digital Twins, as a suite of technologies is progressively developing significant momentum in several fields of study. Various research works have been conducted outlining the concept, the underlying technologies, general and context-specific architectures, and applications. This study has been undertaken to identify relevant research areas, key authors, publishers, and geographical distribution of publications on digital twins through a systematic review and bibliometric analysis, to inform the trajectories of future research in the field. A keyword-based search for journals was first conducted in Web of Science Core Collection to obtain documents relevant for this study, and a systematic review was performed in accordance with the PRISMA guidelines. A bibliometric analysis was then performed on the extracted data using the VOSviewer software. The Tableau software and Microsoft Excel were also used to analyse and visualise some of insights derived from the analysis. © 2022 Elsevier B.V., All rights reserved. | L30: 2022 | M30: 45977.672 | N30: 45980.897 | P30: 105-142 | AA30: Springer | AC30: English | AF30: Scopus | AJ30: Journal Abbreviation: Adv. Sci. Tech. Sec. Appl. DOI: 10.1007/978-3-030-98225-6_5 | AN30: Architecture; Digital twin; Digital twin application; DT; Reference model; included
A31: KG79BWDU | B31: journalArticle | C31: 2024 | D31: Ohueri, C.C.; Masrom, M.A.N.; Seghier, T.E. | E31: Digital twin for decarbonizing operating buildings: A systematic review and implementation framework development | F31: Energy and Buildings | H31: 03787788 (ISSN) | I31: 10.1016/j.enbuild.2024.114567 | J31: https://www.scopus.com/inward/record.uri?eid=2-s2.0-85200210203&doi=10.1016%2Fj.enbuild.2024.114567&partnerID=40&md5=1d09c50942a0181f58ba3b4c6adc5220 | K31: Digital Twin (DT) technology presents a transformative approach to retrofitting practices, with the potential of decarbonizing operating buildings (DOBs) by up to 30 %. However, the fragmented nature of the extensive International Organization for Standardization (ISO) guidelines for carbon assessment and the complexity of DT systems, hinder practitioners’ efforts to fully realize DT's potential in achieving the 2050 zero-emission target for operating buildings. This is evident in the continuous increase in operational carbon emissions from buildings, which reached an all-time high of 10 gigatonnes (GtCO<inf>2</inf>) in 2022, and the mere 13 % global adoption rate of DT in building retrofitting. The aim of this review study is to develop a DT-driven Decarbonization Framework for Operating Buildings (DT-DeFOB) – a pathway for cohesive implementation of complex DT systems for DOBs. Using the inclusion and exclusion method, 243 relevant studies from 2018 to 2023 were selected for scientometrics mapping and systematic literature review (SLR). Furthermore, 20 ISO guidelines were selected for comprehensive document analysis. The findings indicated a growing trajectory in DT literature; however, a limited definitive trend in its effectiveness for DOB was evident. The SLR highlighted a lack of dynamic carbon criteria tailored for operating buildings, as well as a notable absence of a cohesive pathway for implementing multifaceted DT systems in DOBs. Hence, the critical components of DT-DeFOB were established, including a Dynamic Operational Carbon Reduction Guide (DOCReG) – a crucial component of DT-DeFOB developed via document analysis of the 20 selected ISO, Technology Interconnections, Human Engagement, Data Integration, and Lifecycle Management. DT-DeFOB provides a pioneering blueprint to help achieve the construction sector's 2050 net-zero carbon target, presenting a ground-breaking approach for impactful climate change mitigation strategies. © 2024 Elsevier B.V., All rights reserved. | L31: 2024 | M31: 45977.672 | N31: 45980.88 | S31: 320 | U31: Energy Build. | AC31: English | AF31: Scopus | AJ31: Publisher: Elsevier Ltd | AN31: Climate change; Complex systems; Systematic literature review; Buildings; Information management; Data integration; Digital twin; Building decarbonization; Operational carbon reduction; Zero Emission Buildings (ZEBs); Construction industry; Life cycle; Retrofitting; Acidification; Air pollution; Carbon reduction; Decarbonisation; Decarbonising; Decarbonization; Documents analysis; International organization for standardizations; Zero emission building; Zero emission buildings; included
A32: 4WGPM23V | B32: journalArticle | C32: 2024 | D32: Otsu, K.; Masó, J. | E32: Digital Twins for Research and Innovation in Support of the European Green Deal Data Space: A Systematic Review | F32: Remote Sensing | H32: 20724292 (ISSN); 9780891814184 (ISBN); 0891814183 (ISBN); 9780123694072 (ISBN) | I32: 10.3390/rs16193672 | J32: https://www.scopus.com/inward/record.uri?eid=2-s2.0-85206489227&doi=10.3390%2Frs16193672&partnerID=40&md5=afa43be925d957290674064b6bad9b56 | K32: According to the European Data Strategy established in 2020, the European Open Science Cloud (EOSC) is described as “the basis for a science, research and innovation data space… and will be connected and articulated with the sectoral data spaces”, being one of the 14 European Common Data Spaces. While current cross-sectoral interactions with the EOSC are realised through the association’s Health Data Task Force, advancements in other EU priorities, such as the Green Deal and the Digital Strategy, should be accelerated in the green and digital transitions and integrated by reinforcing each other to be climate-neutral by 2050. With this motivation, this paper systematically reviews data spaces and digital twins (DTs) within the context of research and innovation. Specifically, focusing on the relevance of the EOSC to the Green Deal Data Space (GDDS) and DTs of the Earth, the relationship between them is explored using a topic search with various keyword combinations in the Web of Science and CORDIS databases. Based on the selected scientific articles and projects, collaboration opportunities are mapped to connect relevant stakeholders. Furthermore, existing and developing service components that could contribute to technical building blocks for the GDDS are identified. In summary, key findings are highlighted, addressing the current gaps and opportunities among the GDDS initiatives presented in this review. © 2024 Elsevier B.V., All rights reserved. | L32: 2024 | M32: 45977.672 | N32: 45980.879 | R32: 19 | S32: 16 | U32: Remote Sens. | AC32: English | AF32: Scopus | AJ32: Publisher: Multidisciplinary Digital Publishing Institute (MDPI) | AN32: Digital transition; Systematic Review; digital twins; 'current; Data space; data spaces; Destination earth; Destination Earth; digital transition; European green deal; European Green Deal; European open science cloud; European Open Science Cloud; Green development; Open science; Science clouds; Science research; included
A33: 4U3Y96H4 | B33: journalArticle | C33: 2025 | D33: Palley, B.; Poças Martins, J.; Bernardo, H.; Rossetti, R. | E33: Integrating Machine Learning and Digital Twins for Enhanced Smart Building Operation and Energy Management: A Systematic Review | F33: Urban Science | H33: 24138851 (ISSN) | I33: 10.3390/urbansci9060202 | J33: https://www.scopus.com/inward/record.uri?eid=2-s2.0-105008981432&doi=10.3390%2Furbansci9060202&partnerID=40&md5=2278f284959edfdce4dad18669402efe | K33: Artificial Intelligence has recently expanded across various applications. Machine Learning, a subset of Artificial Intelligence, is a powerful technique for identifying patterns in data to support decision making and managing the increasing volume of information. Simultaneously, Digital Twins have been applied in several fields. In this context, combining Digital Twins, Machine Learning, and Smart Buildings offers significant potential to improve energy efficiency and operational effectiveness in building management. This review aims to identify and analyze studies that explore the application of Machine Learning and Digital Twins for operation and energy management in Smart Buildings, providing an updated perspective on these rapidly evolving topics. The methodology follows the PRISMA guidelines for systematic reviews, using Scopus and Web of Science databases. This review identifies the main concepts, objectives, and trends emerging from the literature. Furthermore, the findings confirm the recent growth in research combining Machine Learning and Digital Twins for building management, revealing diverse approaches, tools, methods, and challenges. Finally, this paper highlights existing research gaps and outlines opportunities for future investigation. © 2025 Elsevier B.V., All rights reserved. | L33: 2025 | M33: 45977.672 | N33: 45980.877 | R33: 6 | S33: 9 | U33: Urban. Sci. | AC33: English | AF33: Scopus | AJ33: Publisher: Multidisciplinary Digital Publishing Institute (MDPI) | AN33: machine learning; energy management; digital twins; smart buildings; included
A34: HFWGZ74J | B34: conferencePaper | C34: 2025 | D34: Pişirgen, A.; Areta Hiziroglu, O.A. | E34: Applications of Digital Twin in Precision Medicine: A Systematic Review | F34: Int. Conf. New Trends Comput. Sci., ICTCS | G34: 9798331523411 (ISBN) | I34: 10.1109/ICTCS65341.2025.10989480 | J34: https://www.scopus.com/inward/record.uri?eid=2-s2.0-105007306263&doi=10.1109%2FICTCS65341.2025.10989480&partnerID=40&md5=e0a87df2258595a4ff9171a03970ff8e | K34: Digital twin (DT) technology has emerged as a transformative tool in healthcare and precision medicine, enabling personalized care through real-time simulations, predictive modelling, and patient-specific diagnostics. This systematic review analyses 94 peer-reviewed articles from the Scopus database, highlighting the role of machine learning (ML) techniques—such as supervised, unsupervised, and hybrid methods—in advancing DT applications. The study explores the integration of emerging technologies, including blockchain and generative artificial intelligence (AI), to enhance DT functionality and data security. Spanning disciplines such as cardiology, oncology, neurology, and metabolic disorders, the research underscores the interdisciplinary applications of DTs while addressing critical ethical concerns like data privacy, algorithmic bias, and regulatory challenges. Despite limitations, including reliance on a single database and subjective categorization, this review demonstrates the transformative potential of DTs and suggests future research directions in quantum computing integration and patient-centered DT design. © 2025 Elsevier B.V., All rights reserved. | L34: 2025 | M34: 45977.672 | N34: 45980.873 | P34: 392-399 | AA34: Institute of Electrical and Electronics Engineers Inc. | AC34: English | AF34: Scopus | AJ34: Journal Abbreviation: Int. Conf. New Trends Comput. Sci., ICTCS | AN34: artificial intelligence; digital twin; Predictive models; Systematic Review; Supervised learning; Cardiography; Emerging technologies; Hybrid method; Machine learning techniques; Neurophysiology; Patient specific; precision medicine; Realtime simulation (RTS); Scopus database; Supervised methods; Unsupervised learning; Unsupervised method; included; included.i1
A35: B9JW79B5 | B35: journalArticle | C35: 2024 | D35: Pretel, E.; Moya, A.; Navarro, E.; López-Jaquero, V.; González, P. | E35: Analysing the synergies between Multi-agent Systems and Digital Twins: A systematic literature review | F35: Information and Software Technology | H35: 09505849 (ISSN) | I35: 10.1016/j.infsof.2024.107503 | J35: https://www.scopus.com/inward/record.uri?eid=2-s2.0-85195424921&doi=10.1016%2Fj.infsof.2024.107503&partnerID=40&md5=ce0d2d117645a9406b3858fcfcd59764 | K35: Context: Digital Twins (DTs) are used to augment physical entities by exploiting assorted computational approaches applied to the virtual twin counterpart. A DT is generally described as a physical entity, its virtual counterpart, and the data connections between them. Multi-Agent Systems (MAS) paradigm is alike DTs in many ways. Agents of MAS are entities operating and interacting in a specific environment, while exploring and collecting data to solve some tasks. Objective: This paper presents the results of a systematic literature review (SLR) focused on the analysis of current proposals exploiting the synergies of DTs and MAS. This research aims to synthesize studies that focus on the use of MAS to support DTs development and MAS that exploit DTs, paving the way for future research. Method: A SLR methodology was used to conduct a detailed study analysis of 64 primary studies out of a total of 220 studies that were initially identified. This SLR analyses three research questions related to the synergies between MAS and DT. Results: The most relevant findings of this SLR and their implications for further research are the following: i) most of the analyzed proposals design digital shadows rather than DT; ii) they do not fully support the properties expected from a DT; iii) most of the MAS properties have not fully exploited for the development of DT; iv) ontologies are frequently used for specifying semantic models of the physical twin. Conclusions: Based on the results of this SLR, our conclusions for the community are presented in a research agenda that highlights the need of innovative theoretical proposals and design frameworks that guide the development of DT. They should be defined exploiting the properties of MAS to unleash the full potential of DT. Finally, ontologies for machine learning models should be designed for its use in DT. © 2024 Elsevier B.V., All rights reserved. | L35: 2024 | M35: 45977.672 | N35: 45980.867 | S35: 174 | U35: Inf Software Technol | AC35: English | AF35: Scopus | AJ35: Publisher: Elsevier B.V. | AN35: Internet of things; Internet of Things; Literature review; Systematic literature review; Digital twin; MAS; Multi-agent system; Ontology; 'current; Property; Community IS; Computational approach; Data connection; Literature reviews; Multi agent systems; Ontology's; Research questions; Semantic modelling; Semantics; included
A36: ZJQBKSAQ | B36: journalArticle | C36: 2025 | D36: Rojas, L.; Peña, Á.; Garcia, J. | E36: AI-Driven Predictive Maintenance in Mining: A Systematic Literature Review on Fault Detection, Digital Twins, and Intelligent Asset Management | F36: Applied Sciences (Switzerland) | H36: 20763417 (ISSN) | I36: 10.3390/app15063337 | J36: https://www.scopus.com/inward/record.uri?eid=2-s2.0-105000967139&doi=10.3390%2Fapp15063337&partnerID=40&md5=2ce8ac8861b9263c62ff1948af512185 | K36: The mining industry faces increasing challenges in maintaining high production levels while minimizing unplanned failures and operational costs. Critical assets, such as crushers, conveyor belts, mills, and ventilation systems, operate under extreme conditions, leading to accelerated wear and failure risks. Traditional maintenance strategies often fail to prevent unexpected downtimes, safety hazards, and economic losses. As a response, industries are integrating predictive monitoring technologies, including machine learning, the Internet of Things, and digital twins, to enhance early fault detection and optimize maintenance strategies. This Systematic Literature Review analyzes 166 high-impact studies from Scopus and Web of Science, identifying key trends in fault detection algorithms, hybrid AI models, and real-time monitoring techniques. The findings highlight the increasing adoption of deep learning, reinforcement learning, and digital twins for anomaly detection and process optimization. Additionally, AI-driven methods are improving sensor-based data acquisition and asset management, extending equipment lifecycles while reducing failures. Despite these advancements, challenges such as data standardization, model scalability, and system interoperability persist, requiring further research. Future work should focus on real-time AI applications, explainable models, and academia-industry collaboration to accelerate the implementation of intelligent maintenance solutions, ensuring greater reliability, efficiency, and sustainability in mining operations. © 2025 Elsevier B.V., All rights reserved. | L36: 2025 | M36: 45977.672 | N36: 45980.859 | R36: 6 | S36: 15 | U36: Appl. Sci. | AC36: English | AF36: Scopus | AJ36: Publisher: Multidisciplinary Digital Publishing Institute (MDPI) | AN36: Deep learning; Deep reinforcement learning; Systematic literature review; Predictive maintenance; Asset management; predictive maintenance; Assets management; digital twins; Maintenance strategies; deep learning; Machine-learning; Competition; Belt conveyors; Crushers; Fault detection algorithm; fault detection algorithms; Faults detection; Industrial IoT; Loss prevention; machine learning in mining; Machine learning in mining; Operating costs; Preventive maintenance; Reinforcement learning; Resource valuation; included; included.i1
A37: Z6WDPIB7 | B37: journalArticle | C37: 2025 | D37: Sacoto-Cabrera, E.J.; Pérez-Torres, A.; Tello-Oquendo, L.; Cerrada, M. | E37: IoT, AI, and Digital Twins in Smart Cities: A Systematic Review for a Thematic Mapping and Research Agenda | F37: Smart Cities | H37: 26246511 (ISSN) | I37: 10.3390/smartcities8050175 | J37: https://www.scopus.com/inward/record.uri?eid=2-s2.0-105020198219&doi=10.3390%2Fsmartcities8050175&partnerID=40&md5=23e9e085154401155205b39c42dc136f | K37: Highlights: What are the main findings? This paper presents an SLR comprising the analysis of 64 studies on Urban Digital Twins, IoT, and AI in the development of smart cities using the PRISMA framework. The review identifies three thematic groups and key research points, while revealing gaps such as limited empirical evidence and interoperability challenges. What is the implication of the main finding? This paper highlights the need for integrated, data-driven strategies to improve urban management and policies through Urban Digital Twins, IoT, and AI. The review allows proposing a research agenda to guide future innovations, supporting the development of more sustainable, resilient, and smart cities. The accelerating complexity of urban environments has prompted cities to adopt digital technologies that improve efficiency, sustainability, and resilience. Among these, Urban Digital Twins (UDTw) have emerged as transformative tools for real-time representation, simulation, and management of urban systems. This Systematic Literature Review (SLR) examines the integration of Digital Twins (DTw), the Internet of Things (IoT), and Artificial Intelligence (AI) into the Smart City Development (SCD). Following the PSALSAR framework and PRISMA 2020 guidelines, 64 peer-reviewed articles from IEEE Xplore, Association for Computing Machinery (ACM), Scopus, and Web of Science (WoS) digital libraries were analyzed by using bibliometric and thematic methods via the Bibliometrix package in R. The review allowed identifying key technological trends, such as edge–cloud, architectures, 3D immersive visualization, Generative AI (GenAI), and blockchain, and classifies UDTw applications into five domains: traffic management, urban planning, environmental monitoring, energy systems, and public services. Persistent challenges have been also outlined, including semantic interoperability, predictive modeling, data privacy, and impact evaluation. This study synthesizes the current state of the field, by clearly identifying a thematic mapping, and proposes a research agenda to align technical innovation with measurable urban outcomes, offering strategic insights for researchers, policymakers, and planners. © 2025 Elsevier B.V., All rights reserved. | L37: 2025 | M37: 45977.672 | N37: 45980.856 | R37: 5 | S37: 8 | U37: Smart. Cities. | AC37: English | AF37: Scopus | AJ37: Publisher: Multidisciplinary Digital Publishing Institute (MDPI) | AN37: blockchain; smart cities; Internet of Things (IoT); Artificial Intelligence (AI); Digital Twins (DTw); edge–cloud architecture; interoperability; Systematic Literature Review (SLR); Urban Digital Twins (UDTw); urban planning; included; included.i1
A38: 5I4ZNF27 | B38: journalArticle | C38: 2023 | D38: Sadri, H.; Yitmen, I.; Tagliabue, L.C.; Westphal, F.; Tezel, A.; Taheri, A.; Sibenik, G. | E38: Integration of Blockchain and Digital Twins in the Smart Built Environment Adopting Disruptive Technologies—A Systematic Review | F38: Sustainability (Switzerland) | H38: 20711050 (ISSN) | I38: 10.3390/su15043713 | J38: https://www.scopus.com/inward/record.uri?eid=2-s2.0-85149252247&doi=10.3390%2Fsu15043713&partnerID=40&md5=c5643201463b37d16e10461c9a18b6fb | K38: The integration of blockchain and digital twins (DT) for better building-lifecycle data management has recently received much attention from researchers in the field. In this respect, the adoption of enabling technologies such as artificial intelligence (AI) and machine learning (ML), the Internet of Things (IoT), cloud and edge computing, Big Data analytics, etc., has also been investigated in an abundance of studies. The present review inspects the recent studies to shed light on the foremost among those enabling technologies and their scope, challenges, and integration potential. To this end, 86 scientific papers, recognized and retrieved from the Scopus and Web of Science databases, were reviewed and a thorough bibliometric analysis was performed on them. The obtained results demonstrate the nascency of the research in this field and the necessity of further implementation of practical methods to discover and prove the real potential of these technologies and their fusion. It was also found that the integration of these technologies can be beneficial for addressing the implementation challenges they face individually. In the end, an abstract descriptive model is presented to provide a better understanding of how the technologies can become integrated into a unified system for smartening the built environment. © 2023 Elsevier B.V., All rights reserved. | L38: 2023 | M38: 45977.672 | N38: 45980.851 | R38: 4 | S38: 15 | U38: Sustainability | AC38: English | AF38: Scopus | AJ38: Publisher: MDPI | AN38: artificial intelligence; digital twin; Internet; Internet of Things; machine learning; blockchain; building; data management; implementation process; building industry; technology adoption; technology fusion; included; included.i1
A39: MHBU5LCL | B39: journalArticle | C39: 2021 | D39: Semeraro, C.; Lezoche, M.; Panetto, H.; Dassisti, M. | E39: Digital twin paradigm: A systematic literature review | F39: Computers in Industry | H39: 01663615 (ISSN) | I39: 10.1016/j.compind.2021.103469 | J39: https://www.scopus.com/inward/record.uri?eid=2-s2.0-85105600759&doi=10.1016%2Fj.compind.2021.103469&partnerID=40&md5=41206d190fd9540272f0138326c7f409 | K39: Manufacturing enterprises are facing the need to align themselves to the new information technologies (IT) and respond to the new challenges of variable market demand. One of the key enablers of this IT revolution toward Smart Manufacturing is the digital twin (DT). It embeds a “virtual” image of the reality constantly synchronized with the real operating scenario to provide sound information (knowledge model) to reality interpretation model to draw sound decisions. The paper aims at providing an up-to date picture of the main DT components, their features and interaction problems. The paper aims at clearly tracing the ongoing research and technical challenges in conceiving and building DTs as well, according to different application domains and related technologies. To this purpose, the main questions answered here are: ‘What is a Digital Twin?’; ‘Where is appropriate to use a Digital Twin?’; ‘When has a Digital Twin to be developed?’; ‘Why should a Digital Twin be used?’; ‘How to design and implement a Digital Twin?’; ‘What are the main challenges of implementing a Digital Twin?’. This study tries to answer to the previous questions funding on a wide systematic literature review of scientific research, tools, and technicalities in different application domains. © 2021 Elsevier B.V., All rights reserved. | L39: 2021 | M39: 45977.673 | N39: 45977.921 | S39: 130 | U39: Comput Ind | AC39: English | AF39: Scopus | AJ39: Publisher: Elsevier B.V. | AN39: Industry 4.0; Systematic literature review; Digital twin; Cyber-physical systems; Predictive manufacturing; Smart manufacturing; Manufacture; Design and implements; Interaction problems; Interpretation model; Manufacturing enterprise; Scientific researches; Technical challenges; included; included.i1
A40: CQ3HWA3F | B40: journalArticle | C40: 2025 | D40: Shah, U.M.; Minhas, D.M.; Kifayat, K.; Shah, K.A.; FREY, G. | E40: Threat Modeling and Attacks on Digital Twins of Vehicles: A Systematic Literature Review | F40: Smart Cities | H40: 26246511 (ISSN) | I40: 10.3390/smartcities8050142 | J40: https://www.scopus.com/inward/record.uri?eid=2-s2.0-105020026946&doi=10.3390%2Fsmartcities8050142&partnerID=40&md5=82ccf5690826dde27880a069d354bbe0 | K40: Highlights: What are the main findings? This paper conducts an in-depth review of 23 studies on threat modeling and security testing in automotive digital twins using the PRISMA framework. It identifies deficiencies and proposes improved methodologies to enhance current security and safety validation practices for interconnected automotive systems. What is the implication of the main finding? This paper highlights the need for more advanced threat modeling and emphasizes the importance of improving cybersecurity to prevent potential attacks on connected vehicles. It suggests future research and practical strategies for secure digital twin system design in the automotive sector, supporting the development of resilient smart urban environments through a robust interconnected vehicle security framework. This systematic literature review pioneers the synthesis of cybersecurity challenges for automotive digital twins (DTs), a critical yet underexplored frontier in connected vehicle security. The notion of digital twins, which act as simulated counterparts to real-world systems, is revolutionizing secure system design within the automotive sector. As contemporary vehicles become more dependent on interconnected electronic systems, the likelihood of cyber threats is escalating. This comprehensive literature review seeks to analyze existing research on threat modeling and security testing in automotive digital twins, aiming to pinpoint emerging patterns, evaluate current approaches, and identify future research avenues. Guided by the PRISMA framework, we rigorously analyze 23 studies from 882 publications to address three research questions: (1) How are threats to automotive DTs identified and assessed? (2) What methodologies drive threat modeling? Lastly, (3) what techniques validate threat models and simulate attacks? The novelty of this study lies in its structured classification of digital twin types (physics based, data driven, hybrid), its inclusion of a groundbreaking threat taxonomy across architectural layers (e.g., ECU tampering, CAN-Bus spoofing), the integration of the 5C taxonomy with layered architectures for DT security testing, and its analysis of domain-specific tools such as VehicleLang and embedded intrusion detection systems. The findings expose significant deficiencies in the strength and validation of threat models, highlighting the necessity for more adaptable and comprehensive testing methods. By exposing gaps in scalability, trust, and safety, and proposing actionable solutions aligned with UNECE R155, this SLR delivers a robust framework to advance secure DT development, empowering researchers and industry to fortify vehicle resilience against evolving cyber threats. © 2025 Elsevier B.V., All rights reserved. | L40: 2025 | M40: 45977.672 | N40: 45977.89 | R40: 5 | S40: 8 | U40: Smart. Cities. | AC40: English | AF40: Scopus | AJ40: Publisher: Multidisciplinary Digital Publishing Institute (MDPI) | AN40: risk analysis; attack surface; automotive security; cybersecurity; risk assessment; included; included.i1; inclu
A41: 7MVJQH77 | B41: conferencePaper | C41: 2025 | D41: Soman, S.M.; Golzar, F.; Molinari, M.; Rolando, D. | E41: Digital twins for smart grid connected buildings: A systematic literature review | F41: Proc. ASME Int. Conf. Energy Sustain., ES | G41: 9780791889039 (ISBN) | I41: 10.1115/ES2025-155281 | J41: https://www.scopus.com/inward/record.uri?eid=2-s2.0-105018580210&doi=10.1115%2FES2025-155281&partnerID=40&md5=03938162bda3eb477717015e2572a5b8 | K41: Building and construction sector is responsible for 40% of the total energy consumption and 36% of the total greenhouse gas emissions in the European Union. Digital twin is an emerging digital tool that facilitates building management through data interactions using sensor readings between a physical building and its digital model and improves operation and enhances transparency. However, since the digital twin technologies are not mature and has several challenges associated with it, such as need for extensive data, it is necessary to conduct a systematic literature review on its application to buildings and smart grids. The majority of the current studies look into how digital twins can be used for the management of normal residential or commercial buildings that are connected to conventional electricity grids with little scope for bidirectional power flow. This study conducts a systematic literature review to map the current landscape of research on digital twins in gridinteractive buildings, with a focus on identifying the software tools used in the creation of digital twins for improving energy efficiency. The study uses scientific databases like Scopus and Web of Sciences and has been carried out in accordance with PRISMA guidelines that specify the different steps involved in the methodology to conduct systematic reviews. Autodesk Revit and Artificial Neural Networks emerged as the most common software and technique, based on previous works. © 2025 Elsevier B.V., All rights reserved. | L41: 2025 | M41: 45977.672 | N41: 45977.772 | AA41: American Society of Mechanical Engineers (ASME) | AC41: English | AF41: Scopus | AJ41: Journal Abbreviation: Proc. ASME Int. Conf. Energy Sustain., ES | AN41: Energy efficiency; Reviews; Sustainable development; Energy Efficiency; Systematic literature review; Buildings; Information management; Digital Twin; Digital twin; Smart grid; Construction industry; Intelligent buildings; Smart power grids; Energy; 'current; Digital devices; Office buildings; Construction sectors; Building and construction; Buildings sector; Computer aided software engineering; Computer software; Copyrights; Electric power transmission networks; Energy utilization; Energy-consumption; Grid-connected; Smart Grid; Systematic Literature review; Total energy; included
A42: 4ZHLKLE3 | B42: journalArticle | C42: 2023 | D42: Somers, R.J.; Douthwaite, J.A.; Wagg, D.J.; Walkinshaw, N.; Hierons, R.M. | E42: Digital-twin-based testing for cyber–physical systems: A systematic literature review | F42: Information and Software Technology | H42: 09505849 (ISSN) | I42: 10.1016/j.infsof.2022.107145 | J42: https://www.scopus.com/inward/record.uri?eid=2-s2.0-85145973213&doi=10.1016%2Fj.infsof.2022.107145&partnerID=40&md5=afd871929f6fac05875cf810de436e3f | K42: Context: Cyber–physical systems present a challenge to testers, bringing complexity and scale to safety-critical and collaborative environments. Digital twins enhance these systems through data-driven and simulation based models coupled to physical systems to provide visualisation, predict future states and communication. Due to the coupling between digital and physical worlds, digital twins provide a new perspective into cyber–physical system testing. Objective: The objectives of this study are to summarise the existing literature on digital-twin-based testing. We aim to uncover emerging areas of adoptions, the testing techniques used in these areas and identify future research areas. Method: We conducted a systematic literature review which answered the following research questions: What cyber–physical systems are digital twins currently being used to test? How are test oracles defined for cyber–physical systems? What is the distribution of white-box, black-box and grey-box modelling techniques used for digital twins in the context of testing? How are test cases defined and how does this affect test inputs? Results: We uncovered 26 relevant studies from 480 produced by searching with a curated search query. These studies showed an adoption of digital-twin-based testing following the introduction of digital twins in industry as well as the increasing accessibility of the technology. The oracles used in testing are the digital twin themselves and therefore rely on both system specification and data derivation. Cyber–physical systems are tested through passive testing techniques, as opposed to either active testing through test cases or predictive testing using digital twin prediction. Conclusions: This review uncovers the existing areas in which digital twins are used to test cyber–physical systems as well as outlining future research areas in the field. We outline how the infancy of digital twins has affected their wide variety of definitions, emerging specialised testing and modelling techniques as well as the current lack of predictive ability. © 2023 Elsevier B.V., All rights reserved. | L42: 2023 | M42: 45977.672 | N42: 45977.77 | S42: 156 | U42: Inf Software Technol | AC42: English | AF42: Scopus | AJ42: Publisher: Elsevier B.V. | AN42: Systematic literature review; Digital twin; Cyber-physical systems; Cyber–physical system; Testing; Cybe-physical systems; Modelling techniques; Ability testing; Black-box testing; Collaborative environments; Critical environment; Data simulation; Research areas; Safety engineering; Specifications; Test case; Testing technique; Well testing; included; included.i1
A43: C35LXNJ3 | B43: journalArticle | C43: 2024 | D43: Somma, A.; De Benedictis, A.; Esposito, C.; Mazzocca, N. | E43: The convergence of Digital Twins and Distributed Ledger Technologies: A systematic literature review and an architectural proposal | F43: Journal of Network and Computer Applications | H43: 10958592 (ISSN); 10848045 (ISSN) | I43: 10.1016/j.jnca.2024.103857 | J43: https://www.scopus.com/inward/record.uri?eid=2-s2.0-85186518800&doi=10.1016%2Fj.jnca.2024.103857&partnerID=40&md5=a81535e3de5635c4631f20bbba5c9edf | K43: In recent years, the emerging Digital Twin (DT) technology is playing a key role in fostering the transition towards the Industry 4.0. DTs, representing virtual replicas of physical objects, products or processes established thanks to a bidirectional continuous flow of information between the physical and the virtual world, are currently adopted in multiple domains such as manufacturing, aerospace, automotive, energy, construction, smart cities and smart mobility, etc. DTs live together with the physical system they replicate, receiving the same data and often triggering specific control actions that directly impact on the real system status. When dealing with DTs of complex Cyber-Physical Systems (CPSs), the data sources may be heterogeneous and untrustworthy, which requires the DT to be able to address security issues related to data in transit from/to the physical twin and data at rest. A possible way to address these data security issues consists in adopting Distributed Ledger Technologies (DLTs) which provide several security guarantees on data through cryptographic hashing techniques. In this work, we present a three-fold contribution: (i) we discuss the results of a Systematic Literature Review (SLR) on the state-of-the-art of the research related to the integration between DLT and Digital Twins, aimed at clarifying relevant aspects such as, among others, what is the favourite DLT choice in existing proposals or what is the type of DT-related information to store on-chain; (ii) leveraging the SLR results and other related research, we propose an architectural framework for the integration of DT and DLTs (more specifically, blockchains); (iii) we validate the proposed architecture by means of two proof-of-concept implementations leveraging different technological stacks and taking into account two different operational scenarios. Finally, we conduct a requirements coverage analysis and compare the PoCs through a coverage matrix. © 2024 Elsevier B.V., All rights reserved. | L43: 2024 | M43: 45977.672 | N43: 45977.77 | S43: 225 | U43: J Network Comput Appl | AC43: English | AF43: Scopus | AJ43: Publisher: Academic Press | AN43: Blockchain; Network security; Systematic literature review; Digital Twins; Cybersecurity; Data security; Data trustworthiness; Distributed Ledger Technologies; Reference architecture; Virtual reality; Embedded systems; Cyber Physical System; Physical objects; Block-chain; Continuous-flow; Distributed ledg technology; Distributed ledger; Physical process; Physical products; Security issues; included; included.i1
A44: UL9X8LQG | B44: journalArticle | C44: 2024 | D44: Syed Abdul Rahman, S.A.F.; Abdul Maulud, K.N.; Ujang, U.; Wan Mohd Jaafar, W.S.; Shaharuddin, S.; Ab Rahman, A.A. | E44: The Digital Landscape of Smart Cities and Digital Twins: A Systematic Literature Review of Digital Terrain and 3D City Models in Enhancing Decision-Making | F44: SAGE Open | H44: 21582440 (ISSN) | I44: 10.1177/21582440231220768 | J44: https://www.scopus.com/inward/record.uri?eid=2-s2.0-85182144537&doi=10.1177%2F21582440231220768&partnerID=40&md5=e4645ddb5cfa50150609ee85f59ddd6d | K44: The digitalization of urban mechanisms relies on the integration of digital terrain and 3D city models. However, a systematic examination of this topic within the context of integrated smart cities or digital twins has been lacking, hindering reproducibility and interpretation of results. To address this gap, this study conducts a systematic literature review to explore the role of digital terrain and 3D city models in supporting urban decision-making for integrated smart cities or digital twins. By following a review protocol, research questions were formulated, and systematic search strategies were implemented involving reputable databases such as Scopus, Web of Science, Science Direct, Emerald, Taylor Francis, Springer Link, and Sage Journals. The review process included identification, screening, eligibility assessment, quality appraisal, data extraction, and thematic analysis. The thematic analysis identified eight main themes and 22 sub-themes, shedding light on various aspects of digital terrain and 3D city models in urban decision-making, including (1) data integration and interoperability, (2) integrated visualization; (3) environmental simulation; (4) digital twins application; (5) smart cities application; (6) semantic enrichment; (7) applied planning; and (8) urban planning. This systematic review identifies gaps in the field and provides directions for future studies. © 2024 Elsevier B.V., All rights reserved. | L44: 2024 | M44: 45977.672 | N44: 45977.768 | R44: 1 | S44: 14 | U44: SAGE Open | AC44: English | AF44: Scopus | AJ44: Publisher: SAGE Publications Inc. | AN44: digital twin; smart cities; 3D city model; SLR; digital terrain; included
A45: BQ3SSWTL | B45: journalArticle | C45: 2022 | D45: van Dinter, R.; Tekinerdogan, B.; Catal, C. | E45: Predictive maintenance using digital twins: A systematic literature review | F45: Information and Software Technology | H45: 09505849 (ISSN) | I45: 10.1016/j.infsof.2022.107008 | J45: https://www.scopus.com/inward/record.uri?eid=2-s2.0-85134599958&doi=10.1016%2Fj.infsof.2022.107008&partnerID=40&md5=0a8b3469e8918d3f024bd120171e805d | K45: Context: Predictive maintenance is a technique for creating a more sustainable, safe, and profitable industry. One of the key challenges for creating predictive maintenance systems is the lack of failure data, as the machine is frequently repaired before failure. Digital Twins provide a real-time representation of the physical machine and generate data, such as asset degradation, which the predictive maintenance algorithm can use. Since 2018, scientific literature on the utilization of Digital Twins for predictive maintenance has accelerated, indicating the need for a thorough review. Objective: This research aims to gather and synthesize the studies that focus on predictive maintenance using Digital Twins to pave the way for further research. Method: A systematic literature review (SLR) using an active learning tool is conducted on published primary studies on predictive maintenance using Digital Twins, in which 42 primary studies have been analyzed. Results: This SLR identifies several aspects of predictive maintenance using Digital Twins, including the objectives, application domains, Digital Twin platforms, Digital Twin representation types, approaches, abstraction levels, design patterns, communication protocols, twinning parameters, and challenges and solution directions. These results contribute to a Software Engineering approach for developing predictive maintenance using Digital Twins in academics and the industry. Conclusion: This study is the first SLR in predictive maintenance using Digital Twins. We answer key questions for designing a successful predictive maintenance model leveraging Digital Twins. We found that to this day, computational burden, data variety, and complexity of models, assets, or components are the key challenges in designing these models. © 2022 Elsevier B.V., All rights reserved. | L45: 2022 | M45: 45977.672 | N45: 45977.713 | S45: 151 | U45: Inf Software Technol | AC45: English | AF45: Scopus | AJ45: Publisher: Elsevier B.V. | AN45: Artificial intelligence; Maintenance; Software engineering; Systematic literature review; Digital twin; Active learning; Predictive maintenance; E-learning; Applications domains; Real- time; Scientific literature; Active Learning; Failure data; Learning tool; Maintenance algorithms; Maintenance systems; included
A46: WT7KT2T6 | B46: journalArticle | C46: 2025 | D46: Venkateswarlu, N.; Sathiyamoorthy, M. | E46: Sustainable innovations in digital twin technology: a systematic review about energy efficiency and indoor environment quality in built environment | F46: Frontiers in Built Environment | H46: 22973362 (ISSN) | I46: 10.3389/fbuil.2025.1523464 | J46: https://www.scopus.com/inward/record.uri?eid=2-s2.0-105001738535&doi=10.3389%2Ffbuil.2025.1523464&partnerID=40&md5=4fc7b9fc96641280599c24842151762e | K46: In the contemporary digital age, the built environment undergoes significant changes because of technological innovations that improve building management, optimize building efficiency, and enhance overall productivity. Digital Twin technology has emerged as an indispensable tool for enhancing indoor environmental quality and optimizing energy efficiency in existing buildings. This demonstrates its similarity to several SDGs, where digital twin technology is key to achieving many of them, especially those relevant to our research: 7. Affordable and clean energy; 3. Good health and wellbeing are the primary outcomes of our study; 9. Industry innovation and infrastructure are the focus of our methodology; and 11. Sustainable cities and communication, to which our research contributes. However, some challenges require further consideration. First, to assess the methods and tools used to monitor and represent environmental parameters. Second, to review previous studies on Digital Twin technology in the context of energy efficiency and indoor environmental quality. This study systematically examined 261 academic articles to address these challenges, identifying 17 relevant publications investigating Digital Twin for enhancing energy efficiency and indoor environmental quality in buildings. The research emphasizes Building Information Modeling, Internet of Things, and Big Data, which collectively improve the monitoring and management of physical assets through real-time data replication. Our research illustrates the need for a multidisciplinary framework to rigorously analyze Digital Twin applications, as a comprehensive understanding of the consequences of this technology requires the integration of different fields. The review emphasizes the confined application of sensors for monitoring the environment, the importance of residents subjective impressions, and the need for further comparative studies on energy use estimation methods. For future investigation, enhanced international collaboration is imperative to improve the scholarly exploration of Digital Twin related to this field. Finally, the built environment can benefit significantly from implementing Digital Twin technology. However, the challenges must be addressed before technology can achieve its full potential for creating sustainable and energy-efficient buildings. © 2025 Elsevier B.V., All rights reserved. | L46: 2025 | M46: 45977.672 | N46: 45977.71 | S46: 11 | U46: Front. Built Environ. | AC46: English | AF46: Scopus | AJ46: Publisher: Frontiers Media SA | AN46: digital twin; energy efficiency; bim; buildings; indoor environmental quality; scientometric review; included
A47: B2E9STXD | B47: journalArticle | C47: 2024 | D47: Verdecchia, R.; Scommegna, L.; Picano, B.; Becattini, M.; Vicario, E. | E47: Network Digital Twins: A Systematic Review | F47: IEEE Access | H47: 21693536 (ISSN) | I47: 10.1109/ACCESS.2024.3453034 | J47: https://www.scopus.com/inward/record.uri?eid=2-s2.0-85203658258&doi=10.1109%2FACCESS.2024.3453034&partnerID=40&md5=a3881aec590ef99ef5d89df4523cf655 | K47: Network management is becoming more complex due to various factors. The growth of IoT increases the number of nodes to control. The combination of Edge and Fog Computing with distributed algorithms makes network synchronization challenging. Softwarized technologies simplify network management but create integration issues with legacy networks. Even in industrial settings where drones and mobile robots are used, proper network management is crucial yet challenging. In this context, digital twins can be used to replicate the structure and behavior of the physical network and at the same time can be used to successfully manage the complexity and heterogeneity of current networks. Despite the rapid growth of interest in the topic, a comprehensive overview of Network Digital Twin research is currently missing. To address this gap, in this paper, we present a systematic review of the Network Digital Twin literature. From the analysis of 138 primary studies, various insights emerge. Networking Digital Twin is a particularly recent concept that has been explored in the literature since 2017 and is experiencing a steady increase to this day. The vast majority of the studies propose solutions to optimize network performance, but there are also many oriented towards other goals such as security and functional suitability. The three most recurrent application domains, as self-reported in the primary studies, are those of smart industry, edge computing, and vehicular. The main research topics aim at network optimization, support for offloading, resource allocation, and floor monitoring, but also support in the implementation of machine learning algorithms such as federated learning. As a conclusion, Networking Digital Twin proves to be a promising emerging field both for academics and practitioners. © 2024 Elsevier B.V., All rights reserved. | L47: 2024 | M47: 45977.672 | N47: 45977.701 | P47: 145400-145416 | S47: 12 | U47: IEEE Access | AC47: English | AF47: Scopus | AJ47: Publisher: Institute of Electrical and Electronics Engineers Inc. | AN47: Fog computing; Resource allocation; Systematic literature review; Digital twins; systematic literature review; Systematic Review; Management IS; 'current; computer networks; Industrial settings; Integration issues; Legacy networks; Network synchronization; Networks management; Physical network; included; included.i1
A48: DL25H6FN | B48: journalArticle | C48: 2024 | D48: Vuoto, A.; Funari, M.F.; Lourenço, P.B. | E48: Shaping Digital Twin Concept for Built Cultural Heritage Conservation: A Systematic Literature Review | F48: International Journal of Architectural Heritage | H48: 15583058 (ISSN); 15583066 (ISSN) | I48: 10.1080/15583058.2023.2258084 | J48: https://www.scopus.com/inward/record.uri?eid=2-s2.0-85171773723&doi=10.1080%2F15583058.2023.2258084&partnerID=40&md5=88366de9e7dd8c50d0ba243629e81fbf | K48: The Digital Twin (DT) technology has shown promise in transforming complex engineered systems. However, its adoption in the Architecture, Engineering, Construction, and Operation (AECO) field, particularly for Built Cultural Heritage (BCH) conservation, is still in its early stages. This study presents a systematic literature review of 85 academic publications to evaluate the current state of DT implementation in heritage building conservation and identifies areas for optimising preventive management. In addition, this review explores interpretations of the DT concept in this field, addressing overlaps with Historical/Heritage Building Information Modelling (HBIM), discusses DT functionalities and presents existing frameworks. The findings demonstrate the potential of DT to revolutionise BCH conservation through a holistic approach. However, further focus is needed on features and tools for enhancing performance-based management with targeted strategies and advanced data analysis. Future research should prioritise developing these aspects to fully leverage the potential of the DT paradigm in BCH conservation. © 2024 Elsevier B.V., All rights reserved. | L48: 2024 | M48: 45977.672 | N48: 45977.698 | P48: 1762-1795 | R48: 11 | S48: 18 | U48: Int. J. Archit. Herit. | AC48: English | AF48: Scopus | AJ48: Publisher: Taylor and Francis Ltd. | AN48: literature review; Systematic literature review; Information management; Digital Twin; Decision making; Decisions makings; decision making; Architecture engineering; Engineering operation; Heritage buildings; Build cultural heritage; building; Built cultural heritage; Complex engineered systems; conservation management; cultural heritage; Cultural heritage conservation; Cultural heritages; data management; decision-making; Historic preservation; preventive conservation; Preventive conservation; spatiotemporal analysis; included
A49: 6FABWT4T | B49: journalArticle | C49: 2025 | D49: Weerasinghe, L.N.K.; Darko, A.; Chan, A.P.C.; Xiao, B. | E49: Digital twin for sustainable decision-making in building net zero carbon retrofitting: a systematic review | F49: Built Environment Project and Asset Management | H49: 20441258 (ISSN); 2044124X (ISSN) | I49: 10.1108/BEPAM-03-2025-0090 | J49: https://www.scopus.com/inward/record.uri?eid=2-s2.0-105017136612&doi=10.1108%2FBEPAM-03-2025-0090&partnerID=40&md5=de99655b5d1476f74c18009e75d82ce2 | K49: Purpose – Digital twin (DT) is an innovative concept within the construction sector that utilizes real-world performance data to create a virtual model, enabling optimized decision-making. Building net zero carbon (NZC) retrofitting offers an opportunity to reduce global carbon emissions. However, decision-makers face challenges in making smart and sustainable decisions in NZC retrofitting. DT can improve the smartness and sustainability of the decision-making practice in NZC retrofitting, providing promising solutions. Hence, this study assesses the potential of DT for smart and sustainable decision-making in NZC retrofitting. Design/methodology/approach – This study used a three-stage methodology, which included initial work, systematic review and analysis and discussion. Accordingly, the study investigated 29 relevant academic publications on DT and building retrofitting to NZC, using content analysis as the major analytical approach. Findings – The findings demonstrated the effective application of DT in assessing carbon emissions, energy usage, comfort levels and financial savings within the context of building NZC retrofitting. However, it highlighted a lack of integrated focus on the environmental, social and economic pillars of sustainability in NZC retrofitting. Furthermore, the review identified the technologies utilized in implementing DT for building NZC retrofitting as data-related, modeling-related and model simulation-related technologies. Centered on the identified gaps, the study provides recommendations for building NZC retrofitting. Originality/value – The identified gaps and proposed directions would guide future researchers interested in implementing DT to make sustainable decisions in building NZC retrofitting. © 2025 Elsevier B.V., All rights reserved. | L49: 2025 | M49: 45977.672 | N49: 45977.695 | U49: Built Environ. Proj. Asset Manage. | AC49: English | AF49: Scopus | AJ49: Publisher: Emerald Publishing | AN49: Digital twin; Review; Building; Net zero carbon; Retrofitting; Smart and sustainable decision-making; included
A50: TLN8A6QW | B50: journalArticle | C50: 2023 | D50: Weil, C.; Bibri, S.E.; Longchamp, R.; Golay, F.; Alahi, A. | E50: Urban Digital Twin Challenges: A Systematic Review and Perspectives for Sustainable Smart Cities | F50: Sustainable Cities and Society | H50: 22106707 (ISSN) | I50: 10.1016/j.scs.2023.104862 | J50: https://www.scopus.com/inward/record.uri?eid=2-s2.0-85163715089&doi=10.1016%2Fj.scs.2023.104862&partnerID=40&md5=3a973d54c56975bddbf3bf773c3473a8 | K50: Recent scientific and technological advancements have transformed the knowledge frontiers, giving rise to the next wave of disruptive technologies with deep impacts on urban society. An Urban Digital Twin (UDT) is a technology with great potential to transform the management and planning of the infrastructures and systems of sustainable smart cities towards environmental sustainability. However, despite the recent increase of research on UDTs due to its widespread diffusion much more recently, there is a lack of studies examining the existing bottlenecks to its implementation. To fill this gap, this study provides a systematic literature review on the key challenges and open issues pertaining to the implementation of an UDT. Results indicate 8 important categories of challenges related to (1) interoperability and semantics; (2) infrastructure, including storage, computation, network; (3) data acquisition and actuation; (4) data quality and harmonization; (5) modeling, simulation and decision-support; (6) data visualization and information display; (7) human and capital resources; and finally (8) governance, organizational and social issues. All topics are significantly raised in the literature, with most emphasis on issues pertaining to data and model semantics, missing data, data quality and modeling. The findings serve to inform practitioners about the bottlenecks delaying the implementation of UDTs. © 2023 Elsevier B.V., All rights reserved. | L50: 2023 | M50: 45977.672 | N50: 45977.694 | S50: 99 | U50: Sustainable Cities Soc. | AC50: English | AF50: Scopus | AJ50: Publisher: Elsevier Ltd | AN50: sustainability; Environmental sustainability; Sustainable development; Systematic literature review; Digital twins; Data quality; City management; City planning; Sustainable smart cities; Urban digital twins; Urban planning; Urban digital twin; Smart city; Systematic Review; technological development; urban planning; Decision support systems; urban development; Data visualization; Digital storage; smart city; Sustainable smart city; Technological advancement; Semantics; Data acquisition; Deep impact; Disruptive technology; Environmental technology; implementation process; infrastructural development; included
A51: XZLN82C2 | B51: journalArticle | C51: 2023 | D51: Wooley, A.; Silva, D.F.; Bitencourt, J. | E51: When is a simulation a digital twin? A systematic literature review | F51: Manufacturing Letters | H51: 22138463 (ISSN) | I51: 10.1016/j.mfglet.2023.08.014 | J51: https://www.scopus.com/inward/record.uri?eid=2-s2.0-85173285566&doi=10.1016%2Fj.mfglet.2023.08.014&partnerID=40&md5=2439a457b6b7305947c2c1057c6b7e03 | K51: This paper presents a systematic literature review to analyze the connection between the capabilities of Digital Twin (DT) and simulation; it also reviews industrial applications of DT and its different definitions. After a systematic search of several databases and a careful selection based on established criteria, 120 journal academic publications regarding practical implementations of DT were selected and classified according to the capabilities of DT and/or simulation that they implemented. Based on the results of the SLR classification and analysis, the challenges in this area that are preventing the widespread adoption of a fully capable DT are presented. This work also identifies the current limitations and reasons behind some misconception of DT. There is still a disconnection between the DT concepts and applications, as people continue to construct DTs that are basically simulation models. Furthermore, those that build a DT only make use of a portion of its capabilities. © 2023 Elsevier B.V., All rights reserved. | L51: 2023 | M51: 45977.672 | N51: 45977.685 | P51: 940-951 | S51: 35 | U51: Manuf. Let. | AC51: English | AF51: Scopus | AJ51: Publisher: Elsevier Ltd | AN51: Simulation; Systematic literature review; Digital Twin; Capability; Simulation model; Academic publications; Systematic searches; Circuit simulation; Classifieds; Current limitation; Selection based; included
A52: 7HUG938J | B52: journalArticle | C52: 2023 | D52: Yan, B.; Yang, F.; Qiu, S.; Wang, J.; Cai, B.; Wang, S.; Zaheer, Q.; Wang, W.; Chen, Y.; Hu, W. | E52: Digital twin in transportation infrastructure management: a systematic review | F52: Intelligent Transportation Infrastructure | H52: 27529991 (ISSN) | I52: 10.1093/iti/liad024 | J52: https://www.scopus.com/inward/record.uri?eid=2-s2.0-85189082336&doi=10.1093%2Fiti%2Fliad024&partnerID=40&md5=b23a1c26f1dc1cbd23051abebee84e3c | K52: The concept of digital twin (DT) has emerged as a trend in various industries development, enabling the creation of virtual models of physical objects. We conduct a systematic review of the DT technology in the field of transportation infrastructure management from the aspects of concept definition, whole life cycle application, advanced technology, and equipment utilization, as well as the challenges. We begin with an introduction that defines DT and its components, while also distinguishing it from building information modeling and cyber-physical systems. We explore the diverse applications of DT throughout its lifecycle and highlight the significance of DT in structural monitoring, infrastructure operation and maintenance, and dataset expansion. We further investigate the advanced techniques and equipment associated with DT components, focusing on the importance of virtual parts, data acquisition, transmission, multi-source data fusion processing, and data security as well as dynamic updating of models for effective integration and utilization of DT in transportation infrastructure management. We identify key challenges faced by DT in transportation infrastructure management and propose future trends in the study. This comprehensive review serves as a valuable resource for researchers, practitioners, and decision-makers in understanding the potential of DT technology in transportation infrastructure management. © 2024 Elsevier B.V., All rights reserved. | L52: 2023 | M52: 45977.672 | N52: 45977.684 | S52: 2 | U52: Intell. Transp. Infrastruct. | AC52: English | AF52: Scopus | AJ52: Publisher: Oxford University Press | AN52: digital twin; defect detection; lifecycle management; operations and maintenance; transportation infrastructure management; included
A53: NSZKMPPS | B53: conferencePaper | C53: 2024 | D53: Yan, J.; Lu, Q.; Moretti, N.; Li, N. | E53: A systematic review of generating the common data environment for city-level digital twins | F53: Proc. Int. Workshop Intell. Comput. Eng., EG-ICE | J53: https://www.scopus.com/inward/record.uri?eid=2-s2.0-85207235923&partnerID=40&md5=81d7e06303489f52ab17b75ea2d1799d | K53: The concept of Digital Twin (DT) has been greatly welcomed in Architectural, Engineering, Construction and Facility Management (AEC/FM) sector. From the concept to practice, the most dominant challenge could be the data management. Especially, the potentials of DTs in diverse application scenarios have been proposed from building to infrastructure, and to the city level under the requirements of multiple stakeholders. In this context, the data issues are aggravated facing the increasing heterogeneous data from the physical environment. However, there is limited research works examining and summarizing the data management issues when constructing DTs comprehensively in the AEC/FM sector. Therefore, this study aims to address this knowledge gap. First, a data environment with the enablers of data sources, data ecosystem, and data consumers connecting the physical and virtual spaces is defined. Specifically, the data ecosystem enabler is defined with five functional components (i.e., data collection and ingestion, data process and integration, data analysis and representation, data storage, and data pipelines). Then, 149 academic research works were selected as the data set for the systematic literature review. The review and analysis are conducted based on the structure of the enablers in a data environment. This research intends to bring thorough and practical insights of DTs from building to city level assets for researchers, practitioners, and policy makers. © 2024 Elsevier B.V., All rights reserved. | L53: 2024 | M53: 45977.672 | N53: 45977.682 | P53: 115-124 | AA53: European Group for Intelligent Computing in Engineering (EG-ICE) | AC53: English | AF53: Scopus | AJ53: Journal Abbreviation: Proc. Int. Workshop Intell. Comput. Eng., EG-ICE | AN53: Information management; Data integration; Facilities management; Systematic Review; Application scenario; Architectural engineering constructions; Construction management; Data assimilation; Data environment; Diverse applications; Engineering management; Heterogeneous data; Multiple stakeholders; Plant management; included
A54: SGXJJRTV | B54: journalArticle | C54: 2023 | D54: Yao, J.-F.; Yang, Y.; Wang, X.-C.; Zhang, X.-P. | E54: Systematic review of digital twin technology and applications | F54: Visual Computing for Industry, Biomedicine, and Art | H54: 2096496X (ISSN); 25244442 (ISSN) | I54: 10.1186/s42492-023-00137-4 | J54: https://www.scopus.com/inward/record.uri?eid=2-s2.0-85160690565&doi=10.1186%2Fs42492-023-00137-4&partnerID=40&md5=5d2739346364fd7fe2183c47dc114cf6 | K54: As one of the most important applications of digitalization, intelligence, and service, the digital twin (DT) breaks through the constraints of time, space, cost, and security on physical entities, expands and optimizes the relevant functions of physical entities, and enhances their application value. This phenomenon has been widely studied in academia and industry. In this study, the concept and definition of DT, as utilized by scholars and researchers in various fields of industry, are summarized. The internal association between DT and related technologies is explained. The four stages of DT development history are identified. The fundamentals of the technology, evaluation indexes, and model frameworks are reviewed. Subsequently, a conceptual ternary model of DT based on time, space, and logic is proposed. The technology and application status of typical DT systems are described. Finally, the current technical challenges of DT technology are analyzed, and directions for future development are discussed. © 2023 Elsevier B.V., All rights reserved. | L54: 2023 | M54: 45977.672 | N54: 45977.682 | R54: 1 | S54: 6 | U54: Vis. Comput. Ind. Biomed. Art | AC54: English | AF54: Scopus | AJ54: Publisher: Springer | AN54: Simulation; Information technology; Digital twin; Digitalization; Systematic Review; Virtual models; Time-space; Technologies and applications; Development history; Evaluation index; Evaluation models; Technology evaluation; Virtual modeling; included
A55: AKWCSI3A | B55: journalArticle | C55: 2024 | D55: Yuan, J.; Ma, J.; Tian, Z.; Man, K.L. | E55: Digital Twin Integration With Data Fusion for Enhanced Photovoltaic System Management: A Systematic Literature Review | F55: IEEE Open Journal of Power Electronics | H55: 26441314 (ISSN) | I55: 10.1109/OJPEL.2024.3422021 | J55: https://www.scopus.com/inward/record.uri?eid=2-s2.0-85197498186&doi=10.1109%2FOJPEL.2024.3422021&partnerID=40&md5=54570fa7fa287621337f8435e0104c71 | K55: The integration of Digital Twin (DT) technology into the photovoltaic (PV) sector represents a significant advancement in energy management, optimization, servicing, and maintenance. This comprehensive literature review aims to enhance understanding, categorization, and adoption of DT and data fusion technologies within the PV industry to guide future research endeavors. The review categorizes PV models into three types: digital models, digital shadows, and digital twins, based on their data connection and integration attributes. It recognizes data fusion as the critical enabling technology for the development of complex DT models and proposes a framework for integrating data fusion with DT systems. A detailed examination of prevalent PV modeling methodologies is conducted to delineate their advantages and limitations, serving as a valuable resource for industry practitioners. The paper concludes that digital models and digital shadows are effective for initial PV system forecast and monitoring, while fully integrated DT models offer significant advantages, including real-time analysis, predictive capabilities, and active system optimization. However, implementing and maintaining DT models require advanced data analytics, high computational costs, and robust system security, presenting important challenges to be addressed in future research endeavors. © 2024 Elsevier B.V., All rights reserved. | L55: 2024 | M55: 45977.672 | N55: 45977.68 | P55: 1045-1058 | S55: 5 | U55: IEEE Open J. Power Electron. | AC55: English | AF55: Scopus | AJ55: Publisher: Institute of Electrical and Electronics Engineers Inc. | AN55: Biological system modeling; Systematic literature review; Information management; Data integration; Solar energy; Photovoltaic systems; Digital modeling; Digital shadow; Optimisations; Data fusion; Biological systems; Control systems; Energy model; modeling; Photovoltaic model; photovoltaic power systems; Photovoltaics; solar energy; Solar power generation; Systems management; included
A56: 68Y73VN3 | B56: journalArticle | C56: 2025 | E56: Correction to: Discrete event simulation and Digital Twins in warehouse logistics: a bibliometric and content analysis-based systematic literature review (International Journal of Computer Integrated Manufacturing, (2024), (1-28), 10.1080/0951192X.2024.2314772) | F56: International Journal of Computer Integrated Manufacturing | H56: 0951192X (ISSN); 13623052 (ISSN) | I56: 10.1080/0951192X.2024.2388927 | J56: https://www.scopus.com/inward/record.uri?eid=2-s2.0-85200484581&doi=10.1080%2F0951192X.2024.2388927&partnerID=40&md5=8964775f0e123504cbe40ad4b4282b0e | K56: Article title: Discrete event simulation and Digital Twins in warehouse logistics: a bibliometric and content analysis-based systematic literature review Authors: Aretoulaki, Eleni., Ponis, Stavros., Plakas, George & Tzanetou, Dimitra. Journal: TCIM: International Journal of Computer Integrated ManufacturingDOI: http://dx.doi.org/10.1080/0951192X.2024.2314772 When the article was originally published, the title of the article as follows: (DT4Smart) discrete event simulation and Digital Twins in warehouse logistics: a bibliometric and content analysis-based systematic literature review The current revised article title is: Discrete event simulation and Digital Twins in warehouse logistics: a bibliometric and content analysis-based systematic literature review. © 2025 Elsevier B.V., All rights reserved. | L56: 2025 | M56: 45977.672 | N56: 45977.679 | P56: ii | R56: 6 | S56: 38 | U56: Int J Computer Integr Manuf | V56: Correction to: Discrete event simulation and Digital Twins in warehouse logistics: a bibliometric and content analysis-based systematic literature review (International Journal of Computer Integrated Manufacturing, (2024), 37, 10-11, (1376-1403), 10.1080/0951192X.2024.2314772) | AC56: English | AF56: Scopus | AJ56: Publisher: Taylor and Francis Ltd. | AN56: included

Sheet Página5
A1: ID | B1: DOI | C1: Title | D1: Link | E1: DB
A2: DT.DBQ2.01 | B2: ='scopus_export_Nov 16-2025_filte'!I2 -> 10.1186/s42162-024-00385-5 | C2: ='scopus_export_Nov 16-2025_filte'!E2 -> Digital Twins of smart energy systems: a systematic literature review on enablers, design, management and computational challenges | D2: ='scopus_export_Nov 16-2025_filte'!J2 -> https://www.scopus.com/inward/record.uri?eid=2-s2.0-85205923870&doi=10.1186%2Fs42162-024-00385-5&partnerID=40&md5=806c3f02ba8c9f382702f93b30376aed
A3: DT.DBQ2.02 | B3: ='scopus_export_Nov 16-2025_filte'!I3 -> 10.1016/j.apenergy.2025.126670 | C3: ='scopus_export_Nov 16-2025_filte'!E3 -> A systematic review of transformers and large language models in the energy sector: towards agentic digital twins | D3: ='scopus_export_Nov 16-2025_filte'!J3 -> https://www.scopus.com/inward/record.uri?eid=2-s2.0-105013772709&doi=10.1016%2Fj.apenergy.2025.126670&partnerID=40&md5=c1cad25a7dc752b2dbd6cb8ee9706b33
A4: DT.DBQ2.03 | B4: ='scopus_export_Nov 16-2025_filte'!I4 -> 10.1109/ICISS59129.2023.10291219 | C4: ='scopus_export_Nov 16-2025_filte'!E4 -> A Systematic Literature Review of Recent Trends and Challenges in Digital Twin Implementation | D4: ='scopus_export_Nov 16-2025_filte'!J4 -> https://www.scopus.com/inward/record.uri?eid=2-s2.0-85177460118&doi=10.1109%2FICISS59129.2023.10291219&partnerID=40&md5=a6bc6d3e07f2b2bddf90df9ceb1c59fd
A5: DT.DBQ2.04 | B5: ='scopus_export_Nov 16-2025_filte'!I5 -> 10.18280/ijsdp.200801 | C5: ='scopus_export_Nov 16-2025_filte'!E5 -> Digital Twin Integration in Field Service Management: A Hybrid Systematic Literature Review and Bibliometric Analysis (2017-2024) | D5: ='scopus_export_Nov 16-2025_filte'!J5 -> https://www.scopus.com/inward/record.uri?eid=2-s2.0-105018889828&doi=10.18280%2Fijsdp.200801&partnerID=40&md5=a6858ecf572b9ea40e2bd53c60298ce0
A6: DT.DBQ2.05 | B6: ='scopus_export_Nov 16-2025_filte'!I6 -> 10.3390/su17083560 | C6: ='scopus_export_Nov 16-2025_filte'!E6 -> Analysis of Digital Twin Applications in Energy Efficiency: A Systematic Review | D6: ='scopus_export_Nov 16-2025_filte'!J6 -> https://www.scopus.com/inward/record.uri?eid=2-s2.0-105003656265&doi=10.3390%2Fsu17083560&partnerID=40&md5=15880fe7a56c0315846422e00798a2f4
A7: DT.DBQ2.06 | B7: ='scopus_export_Nov 16-2025_filte'!I7 -> 10.1109/ACCESS.2025.3601615 | C7: ='scopus_export_Nov 16-2025_filte'!E7 -> Technologies, Applications, and Challenges of Digital Twin Across Industries: A Systematic Review of the State-of-the-Art Literature | D7: ='scopus_export_Nov 16-2025_filte'!J7 -> https://www.scopus.com/inward/record.uri?eid=2-s2.0-105013996327&doi=10.1109%2FACCESS.2025.3601615&partnerID=40&md5=77d1ad982062f63bd474c7c3f19c5387
A8: DT.DBQ2.07 | B8: ='scopus_export_Nov 16-2025_filte'!I8 -> 10.1080/10447318.2022.2118189 | C8: ='scopus_export_Nov 16-2025_filte'!E8 -> Digital Twins in Human-Computer Interaction: A Systematic Review | D8: ='scopus_export_Nov 16-2025_filte'!J8 -> https://www.scopus.com/inward/record.uri?eid=2-s2.0-85138270893&doi=10.1080%2F10447318.2022.2118189&partnerID=40&md5=f201ed7ffac05dac9bd2c18e89be14e9
A9: DT.DBQ2.08 | B9: ='scopus_export_Nov 16-2025_filte'!I9 -> 10.1007/978-3-032-03538-7_22 | C9: ='scopus_export_Nov 16-2025_filte'!E9 -> Digital Twin, Digital Shadow or Digital Model? A Systematic Literature Review | D9: ='scopus_export_Nov 16-2025_filte'!J9 -> https://www.scopus.com/inward/record.uri?eid=2-s2.0-105015479266&doi=10.1007%2F978-3-032-03538-7_22&partnerID=40&md5=f4812bfa7bde5366bad1c4f8aa0ac42b
A10: DT.DBQ2.09 | B10: ='scopus_export_Nov 16-2025_filte'!I10 | C10: ='scopus_export_Nov 16-2025_filte'!E10 -> A systematic review of methodologies for developing Digital Twins: Insights and recommendations for effective implementation | D10: ='scopus_export_Nov 16-2025_filte'!J10 -> https://www.scopus.com/inward/record.uri?eid=2-s2.0-85186955788&partnerID=40&md5=69a0173d87c1a6defc9d849b238e4cad
A11: DT.DBQ2.10 | B11: ='scopus_export_Nov 16-2025_filte'!I11 -> 10.3390/app11125519 | C11: ='scopus_export_Nov 16-2025_filte'!E11 -> Sustainability requirements of digital twin-based systems: A meta systematic literature review | D11: ='scopus_export_Nov 16-2025_filte'!J11 -> https://www.scopus.com/inward/record.uri?eid=2-s2.0-85108827458&doi=10.3390%2Fapp11125519&partnerID=40&md5=63dfdb02313f91047730df956c13b858
A12: DT.DBQ2.11 | B12: ='scopus_export_Nov 16-2025_filte'!I12 -> 10.1016/j.jmsy.2025.07.006 | C12: ='scopus_export_Nov 16-2025_filte'!E12 -> AI-enhanced digital twins in maintenance: Systematic review, industrial challenges, and bridging research–practice gaps | D12: ='scopus_export_Nov 16-2025_filte'!J12 -> https://www.scopus.com/inward/record.uri?eid=2-s2.0-105011843823&doi=10.1016%2Fj.jmsy.2025.07.006&partnerID=40&md5=59e79e71eab83ffa0cf8fec10c766bc6
A13: DT.DBQ2.12 | B13: ='scopus_export_Nov 16-2025_filte'!I13 -> 10.1007/s10115-023-01870-1 | C13: ='scopus_export_Nov 16-2025_filte'!E13 -> Data management in digital twins: a systematic literature review | D13: ='scopus_export_Nov 16-2025_filte'!J13 -> https://www.scopus.com/inward/record.uri?eid=2-s2.0-85153108953&doi=10.1007%2Fs10115-023-01870-1&partnerID=40&md5=33e53121b1ddf8796cf152499abf999c
... A56: DT.DBQ2.55 | B56: ='scopus_export_Nov 16-2025_filte'!I56 -> 10.1080/0951192X.2024.2388927 | C56: ='scopus_export_Nov 16-2025_filte'!E56 -> Correction to: Discrete event simulation and Digital Twins in warehouse logistics: a bibliometric and content analysis-based systematic literature review (International Journal of Computer Integrated Manufacturing, (2024), (1-28), 10.1080/0951192X.2024.2314772) | D56: ='scopus_export_Nov 16-2025_filte'!J56 -> https://www.scopus.com/inward/record.uri?eid=2-s2.0-85200484581&doi=10.1080%2F0951192X.2024.2388927&partnerID=40&md5=8964775f0e123504cbe40ad4b4282b0e
B57: ='scopus_export_Nov 16-2025_filte'!I57

Sheet scopus_results
A1: Database | B1: Type | C1: Num | D1: LOG | E1: ='Página5'!$A2 -> DT.DBQ2.01 | F1: ='Página5'!$A3 -> DT.DBQ2.02 | G1: ='Página5'!$A4 -> DT.DBQ2.03 | H1: ='Página5'!$A5 -> DT.DBQ2.04 | I1: ='Página5'!$A6 -> DT.DBQ2.05 | J1: ='Página5'!$A7 -> DT.DBQ2.06 | K1: ='Página5'!$A8 -> DT.DBQ2.07 | L1: ='Página5'!$A9 -> DT.DBQ2.08 | M1: ='Página5'!$A10 -> DT.DBQ2.09 | N1: ='Página5'!$A11 -> DT.DBQ2.10 | O1: ='Página5'!$A12 -> DT.DBQ2.11 | P1: ='Página5'!$A13 -> DT.DBQ2.12 | Q1: ='Página5'!$A14 -> DT.DBQ2.13 | R1: ='Página5'!$A15 -> DT.DBQ2.14 | S1: ='Página5'!$A16 -> DT.DBQ2.15 | T1: ='Página5'!$A17 -> DT.DBQ2.16 | U1: ='Página5'!$A18 -> DT.DBQ2.17 | V1: ='Página5'!$A19 -> DT.DBQ2.18 | W1: ='Página5'!$A20 -> DT.DBQ2.19 | X1: ='Página5'!$A21 -> DT.DBQ2.20 | Y1: ='Página5'!$A22 -> DT.DBQ2.21 | Z1: ='Página5'!$A23 -> DT.DBQ2.22 | AA1: ='Página5'!$A24 -> DT.DBQ2.23 | AB1: ='Página5'!$A25 -> DT.DBQ2.24 | AC1: ='Página5'!$A26 -> DT.DBQ2.25 | AD1: ='Página5'!$A27 -> DT.DBQ2.26 | AE1: ='Página5'!$A28 -> DT.DBQ2.27 | AF1: ='Página5'!$A29 -> DT.DBQ2.28 | AG1: ='Página5'!$A30 -> DT.DBQ2.29 | AH1: ='Página5'!$A31 -> DT.DBQ2.30 | AI1: ='Página5'!$A32 -> DT.DBQ2.31 | AJ1: ='Página5'!$A33 -> DT.DBQ2.32 | AK1: ='Página5'!$A34 -> DT.DBQ2.33 | AL1: ='Página5'!$A35 -> DT.DBQ2.34 | AM1: ='Página5'!$A36 -> DT.DBQ2.35 | AN1: ='Página5'!$A37 -> DT.DBQ2.36 | AO1: ='Página5'!$A38 -> DT.DBQ2.37 | AP1: ='Página5'!$A39 -> DT.DBQ2.38 | AQ1: ='Página5'!$A40 -> DT.DBQ2.39 | AR1: ='Página5'!$A41 -> DT.DBQ2.40 | AS1: ='Página5'!$A42 -> DT.DBQ2.41 | AT1: ='Página5'!$A43 -> DT.DBQ2.42 | AU1: ='Página5'!$A44 -> DT.DBQ2.43 | AV1: ='Página5'!$A45 -> DT.DBQ2.44 | AW1: ='Página5'!$A46 -> DT.DBQ2.45 | AX1: ='Página5'!$A47 -> DT.DBQ2.46 | AY1: ='Página5'!$A48 -> DT.DBQ2.47 | AZ1: ='Página5'!$A49 -> DT.DBQ2.48 | BA1: ='Página5'!$A50 -> DT.DBQ2.49 | BB1: ='Página5'!$A51 -> DT.DBQ2.50 | BC1: ='Página5'!$A52 -> DT.DBQ2.51 | BD1: ='Página5'!$A53 -> DT.DBQ2.52 | BE1: ='Página5'!$A54 -> DT.DBQ2.53 | BF1: ='Página5'!$A55 -> DT.DBQ2.54 | BG1: ='Página5'!$A56 -> DT.DBQ2.55 | BH1: Frequência | BI1: Rank | BJ1: Log(F) | BK1: Log(R) | BL1: C | BM1: Percentual | BN1: Cumulative
A2: Scopus | B2: DB | C2: 1 | D2: =LOG(C2) -> 0 | E2: 1 | G2: 1 | H2: 1 | N2: 1 | O2: 1 | P2: 1 | Q2: 1 | R2: 1 | S2: 1 | U2: 1 | V2: 1 | W2: 1 | X2: 1 | AA2: 1 | AC2: 1 | AD2: 1 | AF2: 1 | AH2: 1 | AJ2: 1 | AK2: 1 | AL2: 1 | AM2: 1 | AN2: 1 | AO2: 1 | AP2: 1 | AS2: 1 | AT2: 1 | AU2: 1 | AV2: 1 | AW2: 1 | AY2: 1 | BA2: 1 | BH2: =SUM(E2:BG2) -> 32 | BI2: =C2 -> 1 | BJ2: =LOG(BH2) -> 1.50515 | BK2: =LOG(BI2) -> 0 | BL2: =BJ2+BK2 -> 1.50515 | BM2: =BH2/SUM($BH$2:$BH$26) -> 0.20382166 | BN2: =BM2 -> 0.20382166
A3: Web of Science | B3: DB | C3: =C2+1 -> 2 | D3: =LOG(C3) -> 0.30103 | E3: 1 | F3: 1 | L3: 1 | N3: 1 | P3: 1 | Q3: 1 | R3: 1 | S3: 1 | U3: 1 | W3: 1 | X3: 1 | AA3: 1 | AB3: 1 | AC3: 1 | AD3: 1 | AF3: 1 | AG3: 1 | AI3: 1 | AK3: 1 | AM3: 1 | AN3: 1 | AO3: 1 | AT3: 1 | AU3: 1 | AY3: 1 | BA3: 1 | BB3: 1 | BH3: =SUM(E3:BG3) -> 27 | BI3: =C3 -> 2 | BJ3: =LOG(BH3) -> 1.4313638 | BK3: =LOG(BI3) -> 0.30103 | BL3: =BJ3+BK3 -> 1.7323938 | BM3: =BH3/SUM($BH$2:$BH$26) -> 0.17197452 | BN3: =BM3+BN2 -> 0.37579618
A4: IEEE Xplore | B4: DB | C4: =C3+1 -> 3 | D4: =LOG(C4) -> 0.47712125 | E4: 1 | F4: 1 | G4: 1 | H4: 1 | I4: 1 | K4: 1 | N4: 1 | P4: 1 | R4: 1 | U4: 1 | Z4: 1 | AA4: 1 | AB4: 1 | AC4: 1 | AD4: 1 | AL4: 1 | AN4: 1 | AQ4: 1 | AS4: 1 | AT4: 1 | AV4: 1 | BH4: =SUM(E4:BG4) -> 21 | BI4: =C4 -> 3 | BJ4: =LOG(BH4) -> 1.3222193 | BK4: =LOG(BI4) -> 0.47712125 | BL4: =BJ4+BK4 -> 1.7993405 | BM4: =BH4/SUM($BH$2:$BH$26) -> 0.13375796 | BN4: =BM4+BN3 -> 0.50955414
A5: Science Direct | B5: DB | C5: =C4+1 -> 4 | D5: =LOG(C5) -> 0.60205999 | G5: 1 | H5: 1 | I5: 1 | L5: 1 | N5: 1 | P5: 1 | Q5: 1 | R5: 1 | V5: 1 | W5: 1 | Z5: 1 | AL5: 1 | AP5: 1 | AQ5: 1 | AS5: 1 | AV5: 1 | BA5: 1 | BH5: =SUM(E5:BG5) -> 17 | BI5: =C5 -> 4 | BJ5: =LOG(BH5) -> 1.2304489 | BK5: =LOG(BI5) -> 0.60205999 | BL5: =BJ5+BK5 -> 1.8325089 | BM5: =BH5/SUM($BH$2:$BH$26) -> 0.10828025 | BN5: =BM5+BN4 -> 0.61783439
A6: ACM | B6: DB | C6: =C5+1 -> 5 | D6: =LOG(C6) -> 0.69897 | F6: 1 | G6: 1 | H6: 1 | K6: 1 | P6: 1 | U6: 1 | Z6: 1 | AL6: 1 | AN6: 1 | AQ6: 1 | AS6: 1 | AV6: 1 | BH6: =SUM(E6:BG6) -> 12 | BI6: =C6 -> 5 | BJ6: =LOG(BH6) -> 1.0791812 | BK6: =LOG(BI6) -> 0.69897 | BL6: =BJ6+BK6 -> 1.7781513 | BM6: =BH6/SUM($BH$2:$BH$26) -> 0.076433121 | BN6: =BM6+BN5 -> 0.69426752
A7: Google Scholar | B7: ST | C7: =C6+1 -> 6 | D7: =LOG(C7) -> 0.77815125 | H7: 1 | I7: 1 | J7: 1 | M7: 1 | N7: 1 | U7: 1 | Y7: 1 | Z7: 1 | AD7: 1 | AX7: 1 | BA7: 1 | BH7: =SUM(E7:BG7) -> 11 | BI7: =C7 -> 6 | BJ7: =LOG(BH7) -> 1.0413927 | BK7: =LOG(BI7) -> 0.77815125 | BL7: =BJ7+BK7 -> 1.8195439 | BM7: =BH7/SUM($BH$2:$BH$26) -> 0.070063694 | BN7: =BM7+BN6 -> 0.76433121
A8: Springer Link | B8: DB | C8: =C7+1 -> 7 | D8: =LOG(C8) -> 0.84509804 | G8: 1 | H8: 1 | I8: 1 | K8: 1 | Z8: 1 | AL8: 1 | AV8: 1 | BH8: =SUM(E8:BG8) -> 7 | BI8: =C8 -> 7 | BJ8: =LOG(BH8) -> 0.84509804 | BK8: =LOG(BI8) -> 0.84509804 | BL8: =BJ8+BK8 -> 1.6901961 | BM8: =BH8/SUM($BH$2:$BH$26) -> 0.044585987 | BN8: =BM8+BN7 -> 0.8089172
A9: Elsevier | B9: DB | C9: =C8+1 -> 8 | D9: =LOG(C9) -> 0.90308999 | F9: 1 | I9: 1 | K9: 1 | L9: 1 | N9: 1 | AP9: 1 | BH9: =SUM(E9:BG9) -> 6 | BI9: =C9 -> 8 | BJ9: =LOG(BH9) -> 0.77815125 | BK9: =LOG(BI9) -> 0.90308999 | BL9: =BJ9+BK9 -> 1.6812412 | BM9: =BH9/SUM($BH$2:$BH$26) -> 0.038216561 | BN9: =BM9+BN8 -> 0.84713376
A10: Taylor & Francis | B10: DB | C10: =C9+1 -> 9 | D10: =LOG(C10) -> 0.95424251 | H10: 1 | K10: 1 | N10: 1 | AV10: 1 | BH10: =SUM(E10:BG10) -> 4 | BI10: =C10 -> 9 | BJ10: =LOG(BH10) -> 0.60205999 | BK10: =LOG(BI10) -> 0.95424251 | BL10: =BJ10+BK10 -> 1.5563025 | BM10: =BH10/SUM($BH$2:$BH$26) -> 0.025477707 | BN10: =BM10+BN9 -> 0.87261146
